{"country":"DE","date":"2022-05-16T00:00:00Z","stories":[{"position":1,"id":"1615938997","url":"https://apps.apple.com/de/story/id1615938997","title":"5 Tipps für Pocket Styler","label":"MEISTER:IN DEINES FACHS","short_description":null,"style":"content","artwork":{"url":"https://is3-ssl.mzstatic.com/image/thumb/Features122/v4/24/bb/86/24bb86cc-48f8-47fc-71ca-a3d1092be5f0/source/3524x2160bb.png","text_colors":["000000","000000","652939","623e47"],"bg_color":"e0ced7","alpha":false},"video_preview_url":null,"apps":[{"app_id":1480191929,"name":"Pocket Styler: Fashion Stars","publisher_id":"348389028","publisher_name":"Nordcurrent UAB","categories":[6014,6012,7015,7003],"subtitle":"Dein Modeerfolg beginnt JETZT!","icon_url":"https://is3-ssl.mzstatic.com/image/thumb/Purple112/v4/72/31/97/72319706-4932-7571-b228-e62b09d16905/AppIcon-0-0-1x_U007emarketing-0-0-0-7-0-0-sRGB-0-0-0-GLES2_U002c0-512MB-85-220-0-0.png/1024x1024bb.png","offer":{"action_text":"LADEN","price":0,"price_formatted":"0,00 €"},"on_card":true}],"substyle":"editorial"},{"position":2,"id":"1492287158","url":"https://apps.apple.com/de/story/id1492287158","title":"Was wir gerade spielen","label":"UNSERE FAVORITEN","short_description":"Die besten Spiele der Woche aus dem App Store.","style":"content","artwork":null,"video_preview_url":null,"apps":[{"app_id":1145275343,"name":"Super Mario Run","publisher_id":"1062496488","publisher_name":"Nintendo Co., Ltd.","categories":[6014,7001,7003],"subtitle":"Steuere Mario durch Antippen!","icon_url":"https://is4-ssl.mzstatic.com/image/thumb/Purple116/v4/68/0f/3f/680f3f24-d614-adf9-6f4c-651f0b53fc51/AppIcon-0-0-1x_U007emarketing-0-0-0-7-0-0-sRGB-0-0-0-GLES2_U002c0-512MB-85-220-0-0.png/1024x1024bb.png","offer":{"action_text":"LADEN","price":0,"price_formatted":"0,00 €"},"on_card":true},{"app_id":1590319959,"name":"Dislyte","publisher_id":"1590319961","publisher_name":"Lilith Games International","categories":[6014],"subtitle":"Urbanes Mythologie-RPG","icon_url":"https://is4-ssl.mzstatic.com/image/thumb/Purple126/v4/5b/59/b6/5b59b610-4e4a-2e36-068d-9eb6160bb89c/AppIcon-0-0-1x_U007emarketing-0-0-0-7-0-0-sRGB-0-0-0-GLES2_U002c0-512MB-85-220-0-0.png/1024x1024bb.png","offer":{"action_text":"LADEN","price":0,"price_formatted":"0,00 €"},"on_card":true},{"app_id":1053012308,"name":"Clash Royale","publisher_id":"488106216","publisher_name":"Supercell","categories":[6014,7017,6016,7001],"subtitle":"Epische PvP-Kämpfe in Echtzeit","icon_url":"https://is4-ssl.mzstatic.com/image/thumb/Purple122/v4/89/8c/86/898c86b8-11d5-4268-b235-3bbcf553ae43/AppIcon-1x_U007emarketing-6-0-85-220.png/1024x1024bb.png","offer":{"action_text":"LADEN","price":0,"price_formatted":"0,00 €"},"on_card":true},{"app_id":543186831,"name":"8 Ball Pool™","publisher_id":"337457683","publisher_name":"Miniclip.com","categories":[6014,6016,7016,7015],"subtitle":"Spiele Billard mit Freunden!","icon_url":"https://is3-ssl.mzstatic.com/image/thumb/Purple112/v4/ee/71/39/ee713951-2ef7-2ba3-f157-88f6976c3237/AppIcon-0-0-1x_U007emarketing-0-0-0-7-0-0-sRGB-0-0-0-GLES2_U002c0-512MB-85-220-0-0.png/1024x1024bb.png","offer":{"action_text":"LADEN","price":0,"price_formatted":"0,00 €"},"on_card":true},{"app_id":1433784188,"name":"SpongeBob: Krosses Kochduell","publisher_id":"1095401785","publisher_name":"Tilting Point LLC","categories":[6014,7015,7017],"subtitle":"Burger-Simulator & Kochspiele","icon_url":"https://is1-ssl.mzstatic.com/image/thumb/Purple122/v4/43/12/1c/43121c4f-ece2-d51a-0f59-543444ee2cab/AppIcon-1x_U007emarketing-0-7-0-85-220.png/1024x1024bb.png","offer":{"action_text":"LADEN","price":0,"price_formatted":"0,00 €"},"on_card":true},{"app_id":608206510,"name":"Farm Heroes Saga","publisher_id":"526656015","publisher_name":"King","categories":[6014,6016,7012,7003],"subtitle":"Match 3 Puzzle im Bauernhof","icon_url":"https://is2-ssl.mzstatic.com/image/thumb/Purple122/v4/d7/a7/e4/d7a7e43b-c8ea-a58f-8aa6-6da621d149a6/AppIcon-1x_U007emarketing-0-7-0-85-220.png/1024x1024bb.png","offer":{"action_text":"LADEN","price":0,"price_formatted":"0,00 €"},"on_card":true},{"app_id":1500726361,"name":"Bullet Echo","publisher_id":"450542236","publisher_name":"ZeptoLab UK Limited","categories":[6014,7002,7001],"subtitle":"Stealth-Battle-Royale-Arena","icon_url":"https://is3-ssl.mzstatic.com/image/thumb/Purple122/v4/af/25/4a/af254a94-7024-70b1-6e85-74836331c1f7/AppIcon-0-0-1x_U007emarketing-0-0-0-10-0-0-sRGB-0-0-0-GLES2_U002c0-512MB-85-220-0-0.png/1024x1024bb.png","offer":{"action_text":"LADEN","price":0,"price_formatted":"0,00 €"},"on_card":true},{"app_id":1094591345,"name":"Pokémon GO","publisher_id":"1037205060","publisher_name":"Niantic, Inc.","categories":[6014,7017,7014,6013],"subtitle":"Suche weltweit Pokémon","icon_url":"https://is3-ssl.mzstatic.com/image/thumb/Purple122/v4/d4/38/b2/d438b2b1-dabd-614c-a476-ed148600b08b/AppIcon-1x_U007emarketing-0-7-0-85-220.png/1024x1024bb.png","offer":{"action_text":"LADEN","price":0,"price_formatted":"0,00 €"},"on_card":true},{"app_id":1287282214,"name":"Call of Duty®: Mobile","publisher_id":"285005466","publisher_name":"Activision Publishing, Inc.","categories":[6014,7001],"subtitle":"Battle Royale, Scharfschützen","icon_url":"https://is1-ssl.mzstatic.com/image/thumb/Purple122/v4/f7/db/58/f7db5888-a695-719a-3f73-c587a0c05c8f/AppIcon-1x_U007emarketing-0-9-0-85-220.png/1024x1024bb.png","offer":{"action_text":"LADEN","price":0,"price_formatted":"0,00 €"},"on_card":true},{"app_id":1453651052,"name":"Archero","publisher_id":"1422308796","publisher_name":"HABBY","categories":[6014,7003,7001],"subtitle":"Hit and Run, Win Win Win!","icon_url":"https://is2-ssl.mzstatic.com/image/thumb/Purple112/v4/92/00/9c/92009c45-9b3d-0f09-e976-3a02efd81b9f/AppIcon-0-0-1x_U007emarketing-0-0-0-7-0-0-sRGB-0-0-0-GLES2_U002c0-512MB-85-220-0-0.png/1024x1024bb.png","offer":{"action_text":"LADEN","price":0,"price_formatted":"0,00 €"},"on_card":true},{"app_id":1526121033,"name":"Rush Royale - Tower Defense TD","publisher_id":"875810767","publisher_name":"MY COM","categories":[6014,7017,6016,7005],"subtitle":"Ein Turmverteidigungsspiel","icon_url":"https://is3-ssl.mzstatic.com/image/thumb/Purple122/v4/4a/94/54/4a9454fb-696c-6d18-7a58-d52d468d905c/AppIcon-0-0-1x_U007emarketing-0-0-0-7-0-0-sRGB-0-0-0-GLES2_U002c0-512MB-85-220-0-0.png/1024x1024bb.png","offer":{"action_text":"LADEN","price":0,"price_formatted":"0,00 €"},"on_card":true},{"app_id":1543204967,"name":"Machinika Museum","publisher_id":"608306412","publisher_name":"Plug In Digital","categories":[6014,7012,6016,7002],"subtitle":"Mystery-Rätsel-Spiel","icon_url":"https://is1-ssl.mzstatic.com/image/thumb/Purple112/v4/3f/4a/43/3f4a4302-1b09-cc05-fc83-c27a02f0ef4b/AppIcon-1x_U007emarketing-0-7-0-85-220.png/1024x1024bb.png","offer":{"action_text":"LADEN","price":0,"price_formatted":"0,00 €"},"on_card":true},{"app_id":1330123889,"name":"PUBG MOBILE","publisher_id":"504515421","publisher_name":"Tencent Mobile International Limited","categories":[6014,7001,7017],"subtitle":"Top Battle Royale-Mobilspiel","icon_url":"https://is2-ssl.mzstatic.com/image/thumb/Purple116/v4/c7/4a/80/c74a801f-8301-13ee-90a9-0fcdb982673a/AppIcon-1x_U007emarketing-0-0-GLES2_U002c0-512MB-sRGB-0-0-0-85-220-0-0-0-8.png/1024x1024bb.png","offer":{"action_text":"LADEN","price":0,"price_formatted":"0,00 €"},"on_card":true},{"app_id":431946152,"name":"ROBLOX","publisher_id":"431946155","publisher_name":"Roblox Corporation","categories":[6014,7002,7001,6016],"subtitle":"Entdecke Millionen Erlebnisse","icon_url":"https://is2-ssl.mzstatic.com/image/thumb/Purple122/v4/d3/6e/d5/d36ed56f-b3d4-c99c-8362-4fd28e8b3529/AppIcon-1x_U007emarketing-0-7-0-0-85-220.png/1024x1024bb.png","offer":{"action_text":"LADEN","price":0,"price_formatted":"0,00 €"},"on_card":true},{"app_id":1542340137,"name":"Doodle Jump 2","publisher_id":"285874818","publisher_name":"Lima Sky","categories":[6014,7001,7002],"subtitle":"ACHTUNG: Wahnsinnig süchtig!","icon_url":"https://is2-ssl.mzstatic.com/image/thumb/Purple116/v4/e2/56/0e/e2560e7d-c8f5-a212-a241-53faa31804fe/AppIcon-0-0-1x_U007emarketing-0-0-0-7-0-0-sRGB-0-0-0-GLES2_U002c0-512MB-85-220-0-0.png/1024x1024bb.png","offer":{"action_text":"LADEN","price":0,"price_formatted":"0,00 €"},"on_card":true},{"app_id":1290010412,"name":"NARUTO X BORUTO NINJA VOLTAGE","publisher_id":"352305770","publisher_name":"Bandai Namco Entertainment Inc.","categories":[6014,6016,7001,7017],"subtitle":null,"icon_url":"https://is4-ssl.mzstatic.com/image/thumb/Purple112/v4/d4/dc/d0/d4dcd0ce-1de1-1c14-42d8-e3c034bd28a4/AppIcon-0-0-1x_U007emarketing-0-0-0-7-0-0-sRGB-0-0-0-GLES2_U002c0-512MB-85-220-0-0.png/1024x1024bb.png","offer":{"action_text":"LADEN","price":0,"price_formatted":"0,00 €"},"on_card":true},{"app_id":664575829,"name":"Fishdom","publisher_id":"1162116447","publisher_name":"Playrix","categories":[6014,7012,6016,7015],"subtitle":"Erschaffe dein Traum-Aquarium","icon_url":"https://is2-ssl.mzstatic.com/image/thumb/Purple116/v4/5d/36/78/5d367815-f1e9-cbd0-d085-839895ccf3f9/AppIcon-1x_U007emarketing-0-6-0-85-220.png/1024x1024bb.png","offer":{"action_text":"LADEN","price":0,"price_formatted":"0,00 €"},"on_card":true},{"app_id":1164507836,"name":"RollerCoaster Tycoon® Touch™","publisher_id":"291286181","publisher_name":"Atari","categories":[6014,6016,7017,7015],"subtitle":"Baue einen Freizeitpark","icon_url":"https://is5-ssl.mzstatic.com/image/thumb/Purple122/v4/41/39/27/413927cb-661e-87f4-9300-bdc5aafc4482/AppIcon-0-0-1x_U007emarketing-0-0-0-7-0-0-sRGB-0-0-0-GLES2_U002c0-512MB-85-220-0-0.png/1024x1024bb.png","offer":{"action_text":"LADEN","price":0,"price_formatted":"0,00 €"},"on_card":true},{"app_id":1482155847,"name":"Royal Match","publisher_id":"1482155846","publisher_name":"Dream Games, Ltd.","categories":[6014,7003,7012],"subtitle":"Wische Farben & löse Rätsel","icon_url":"https://is5-ssl.mzstatic.com/image/thumb/Purple112/v4/f3/53/5c/f3535c45-bc96-8dcc-5698-c288c2abedf0/AppIcon-0-0-1x_U007emarketing-0-0-0-7-0-0-sRGB-0-0-0-GLES2_U002c0-512MB-85-220-0-0.png/1024x1024bb.png","offer":{"action_text":"LADEN","price":0,"price_formatted":"0,00 €"},"on_card":true},{"app_id":1508275130,"name":"Mad Skills Motocross 3","publisher_id":"410229365","publisher_name":"Turborilla","categories":[6014,7013,7001],"subtitle":"Motorrad Spiel","icon_url":"https://is4-ssl.mzstatic.com/image/thumb/Purple122/v4/b4/ee/6f/b4ee6f09-4f7f-ae68-3ad6-c713064a7e95/AppIcon-0-0-1x_U007emarketing-0-0-0-7-0-0-sRGB-0-0-0-GLES2_U002c0-512MB-85-220-0-0.png/1024x1024bb.png","offer":{"action_text":"LADEN","price":0,"price_formatted":"0,00 €"},"on_card":true},{"app_id":1521483641,"name":"Beatstar","publisher_id":"1454690169","publisher_name":"Space Ape Ltd","categories":[6014,7011,7003,6011],"subtitle":"Touch Your Music","icon_url":"https://is2-ssl.mzstatic.com/image/thumb/Purple112/v4/b4/b6/95/b4b695ae-006e-9dc4-45c4-aa1f05cdea50/AppIcon-1x_U007emarketing-0-7-0-85-220.png/1024x1024bb.png","offer":{"action_text":"LADEN","price":0,"price_formatted":"0,00 €"},"on_card":false},{"app_id":714796093,"name":"Cooking Fever: Restaurantspiel","publisher_id":"348389028","publisher_name":"Nordcurrent UAB","categories":[6014,6016,7003,7017],"subtitle":"Fesselndes Zeitmanagementspiel","icon_url":"https://is1-ssl.mzstatic.com/image/thumb/Purple122/v4/77/7b/d3/777bd31c-4a2c-54c9-c945-d46a0d465ca6/AppIcon-0-0-1x_U007emarketing-0-0-0-7-0-0-sRGB-0-0-0-GLES2_U002c0-512MB-85-220-0-0.png/1024x1024bb.png","offer":{"action_text":"LADEN","price":0,"price_formatted":"0,00 €"},"on_card":false},{"app_id":1604207548,"name":"Riddle Road","publisher_id":"1568120076","publisher_name":"VIZOR APPS LTD","categories":[6014,7003,6016,7012],"subtitle":"Chill mal & löse tolle Rätsel","icon_url":"https://is4-ssl.mzstatic.com/image/thumb/Purple122/v4/b2/8e/a4/b28ea4ab-3df7-eea3-d82f-d46aaef344ee/AppIcon-0-0-1x_U007emarketing-0-0-0-10-0-0-sRGB-0-0-0-GLES2_U002c0-512MB-85-220-0-0.png/1024x1024bb.png","offer":{"action_text":"LADEN","price":0,"price_formatted":"0,00 €"},"on_card":false}],"substyle":"list"},{"position":3,"id":"1577807762","url":"https://apps.apple.com/de/story/id1577807762","title":"Spiele zum Abschalten","label":"SPIELE IM ALLTAG","short_description":"Diese entspannten Games bringen dich sicher nicht ins Schwitzen.","style":"media","artwork":null,"video_preview_url":"https://is4-ssl.mzstatic.com/image/thumb/Video125/v4/65/51/16/65511655-96ad-122d-6278-275ba90543d8/Jobee4331b3-cf92-4ed7-816b-dbc066f0cec8-118122139-PreviewImage_preview_image_nonvideo_sdr-Time1627400284515.png/2732x2048bb.png","apps":[{"app_id":1524699590,"name":"Tides: A Fishing Game","publisher_id":"916624104","publisher_name":"Shallot Games, LLC.","categories":[6014,7003,7015],"subtitle":null,"icon_url":"https://is3-ssl.mzstatic.com/image/thumb/Purple116/v4/98/a6/77/98a67710-3095-850f-bfa3-79a3d3a46da7/AppIcon-0-0-1x_U007emarketing-0-0-0-7-0-0-sRGB-0-0-0-GLES2_U002c0-512MB-85-220-0-0.png/1024x1024bb.png","offer":{"action_text":"LADEN","price":0,"price_formatted":"0,00 €"},"on_card":true},{"app_id":923917775,"name":"Neko Atsume: Kitty Collector","publisher_id":"495637387","publisher_name":"Hit-Point Co., Ltd.","categories":[6014,7004,7015],"subtitle":null,"icon_url":"https://is4-ssl.mzstatic.com/image/thumb/Purple122/v4/fc/54/89/fc548930-eedd-9e18-a516-762ba03c49c8/AppIcon-1x_U007emarketing-0-6-0-85-220.png/1024x1024bb.png","offer":{"action_text":"LADEN","price":0,"price_formatted":"0,00 €"},"on_card":true},{"app_id":1561912922,"name":"Idle Barber Shop Tycoon Spiel","publisher_id":"516547990","publisher_name":"Digital Things","categories":[6014,6016,7015],"subtitle":"Betreibe einen Friseursalon","icon_url":"https://is4-ssl.mzstatic.com/image/thumb/Purple125/v4/d7/34/d6/d734d627-91b8-6908-30d1-166fa6f3dbae/AppIcon-0-0-1x_U007emarketing-0-0-0-7-0-0-sRGB-0-0-0-GLES2_U002c0-512MB-85-220-0-0.png/1024x1024bb.png","offer":{"action_text":"LADEN","price":0,"price_formatted":"0,00 €"},"on_card":true},{"app_id":1474314811,"name":"Pinguininsel","publisher_id":"1422308796","publisher_name":"HABBY","categories":[6014,7015,6012,7009],"subtitle":"Chill and relax with Penguins","icon_url":"https://is2-ssl.mzstatic.com/image/thumb/Purple116/v4/94/c8/ae/94c8ae94-c8a0-ca54-4451-8c4b238091cd/AppIcon-0-0-1x_U007emarketing-0-0-0-7-0-0-sRGB-0-0-0-GLES2_U002c0-512MB-85-220-0-0.png/1024x1024bb.png","offer":{"action_text":"LADEN","price":0,"price_formatted":"0,00 €"},"on_card":true},{"app_id":1476378632,"name":"Let's Create! Pottery 2","publisher_id":"306712040","publisher_name":"Infinite Dreams Inc.","categories":[6014,7009,6016,7003],"subtitle":null,"icon_url":"https://is1-ssl.mzstatic.com/image/thumb/Purple112/v4/3a/0e/b9/3a0eb984-6dbf-798f-3054-a4ba0145afdc/AppIcon-1x_U007emarketing-0-7-0-85-220.png/1024x1024bb.png","offer":{"action_text":"LADEN","price":0,"price_formatted":"0,00 €"},"on_card":false},{"app_id":1564146071,"name":"Tsukis Odyssee","publisher_id":"1169188578","publisher_name":"HyperBeard Inc.","categories":[6014,7018,7015,6016],"subtitle":"Charmante Idle-Farm-Simulation","icon_url":"https://is2-ssl.mzstatic.com/image/thumb/Purple116/v4/55/6b/5a/556b5aff-1158-d668-d247-eccb445d2055/AppIcon-0-0-1x_U007emarketing-0-0-0-7-0-0-sRGB-0-0-0-GLES2_U002c0-512MB-85-220-0-0.png/1024x1024bb.png","offer":{"action_text":"LADEN","price":0,"price_formatted":"0,00 €"},"on_card":false},{"app_id":1441021951,"name":"Idle Coffee Corp","publisher_id":"1228073651","publisher_name":"Starberry Games GmbH","categories":[6014,7015,7017],"subtitle":"Verwalte dein Kaffee-Imperium!","icon_url":"https://is2-ssl.mzstatic.com/image/thumb/Purple126/v4/af/07/50/af07500a-6e79-022c-bb5d-415a5f71e849/AppIcon-0-0-1x_U007emarketing-0-0-0-7-0-0-sRGB-0-0-0-GLES2_U002c0-512MB-85-220-0-0.png/1024x1024bb.png","offer":{"action_text":"LADEN","price":0,"price_formatted":"0,00 €"},"on_card":false},{"app_id":1492928510,"name":"1sland","publisher_id":"1157484553","publisher_name":"nada studio, sl","categories":[6014,7017,7002],"subtitle":"Paddle Royale","icon_url":"https://is5-ssl.mzstatic.com/image/thumb/Purple122/v4/af/e8/db/afe8dbae-1d24-fb0b-95e3-3d5d5483d277/AppIcon-1x_U007emarketing-0-7-0-85-220.png/1024x1024bb.png","offer":{"action_text":"LADEN","price":0,"price_formatted":"0,00 €"},"on_card":false},{"app_id":1479539390,"name":"Idle King Ritter Spiele Tycoon","publisher_id":"1479539389","publisher_name":"Motap UG (haftungsbeschränkt)","categories":[6014,7017,7015,6016],"subtitle":"Auto Clicker Heroes Tap Games","icon_url":"https://is1-ssl.mzstatic.com/image/thumb/Purple116/v4/dc/8d/a4/dc8da4f1-8b00-fbfc-4b66-e0b59f53cc26/AppIcon-0-0-1x_U007emarketing-0-0-0-7-0-0-sRGB-0-0-0-GLES2_U002c0-512MB-85-220-0-0.png/1024x1024bb.png","offer":{"action_text":"LADEN","price":0,"price_formatted":"0,00 €"},"on_card":false},{"app_id":1531189104,"name":"Idle Museum: History & Science","publisher_id":"1435697032","publisher_name":"Pixodust Aplicativos","categories":[6014,6016,7009,7015],"subtitle":"Lass uns ein Museum bauen!","icon_url":"https://is3-ssl.mzstatic.com/image/thumb/Purple112/v4/55/fc/f3/55fcf3d9-af68-243f-aa8b-3fe9efd4941c/AppIcon-0-0-1x_U007emarketing-0-0-0-7-0-0-sRGB-0-0-0-GLES2_U002c0-512MB-85-220-0-0.png/1024x1024bb.png","offer":{"action_text":"LADEN","price":0,"price_formatted":"0,00 €"},"on_card":false},{"app_id":1247889896,"name":"My Oasis :Entspannungsspiel","publisher_id":"828994637","publisher_name":"Buff Studio Co.Ltd.","categories":[6014,7009,6013,7015],"subtitle":"Angst Linderung App","icon_url":"https://is1-ssl.mzstatic.com/image/thumb/Purple125/v4/c9/03/39/c903392f-64fc-d762-523c-f227d2c5ae6b/AppIcon-0-0-1x_U007emarketing-0-0-0-7-0-0-sRGB-0-0-0-GLES2_U002c0-512MB-85-220-0-0.png/1024x1024bb.png","offer":{"action_text":"LADEN","price":0,"price_formatted":"0,00 €"},"on_card":false},{"app_id":1480191929,"name":"Pocket Styler: Fashion Stars","publisher_id":"348389028","publisher_name":"Nordcurrent UAB","categories":[6014,6012,7015,7003],"subtitle":"Dein Modeerfolg beginnt JETZT!","icon_url":"https://is3-ssl.mzstatic.com/image/thumb/Purple112/v4/72/31/97/72319706-4932-7571-b228-e62b09d16905/AppIcon-0-0-1x_U007emarketing-0-0-0-7-0-0-sRGB-0-0-0-GLES2_U002c0-512MB-85-220-0-0.png/1024x1024bb.png","offer":{"action_text":"LADEN","price":0,"price_formatted":"0,00 €"},"on_card":false},{"app_id":1560178364,"name":"Idle Firefighter Tycoon","publisher_id":"1112983227","publisher_name":"Kolibri Games GmbH","categories":[6014,7015,7003],"subtitle":"Notruf & Feuerwehr Simulator","icon_url":"https://is4-ssl.mzstatic.com/image/thumb/Purple116/v4/40/c7/ad/40c7ad5c-d11d-03ce-f7f9-1237c93ec7ba/AppIcon-0-0-1x_U007emarketing-0-0-0-7-0-0-sRGB-0-0-0-GLES2_U002c0-512MB-85-220-0-0.png/1024x1024bb.png","offer":{"action_text":"LADEN","price":0,"price_formatted":"0,00 €"},"on_card":false},{"app_id":1572251659,"name":"Idle Trading Empire","publisher_id":"1292539616","publisher_name":"Bling Bling Games GmbH","categories":[6014,7015,6016,7017],"subtitle":"Produktion & Transport Manager","icon_url":"https://is1-ssl.mzstatic.com/image/thumb/Purple112/v4/7a/ed/0d/7aed0dd9-e06c-42df-8def-370c89b48c86/AppIcon-0-0-1x_U007emarketing-0-0-0-7-0-0-sRGB-0-0-0-GLES2_U002c0-512MB-85-220-0-0.png/1024x1024bb.png","offer":{"action_text":"LADEN","price":0,"price_formatted":"0,00 €"},"on_card":false},{"app_id":1204231646,"name":"Swim Out","publisher_id":"937331328","publisher_name":"Lozange Lab","categories":[6014,7012,6016,7009],"subtitle":"Escape from the swimming pool","icon_url":"https://is1-ssl.mzstatic.com/image/thumb/Purple114/v4/26/3e/3e/263e3e66-9281-769c-8ba2-9117a01de053/AppIcon-0-0-1x_U007emarketing-0-0-0-7-0-0-sRGB-0-0-0-GLES2_U002c0-512MB-85-220-0-0.png/1024x1024bb.png","offer":{"action_text":"KAUFEN","price":299,"price_formatted":"2,99 €"},"on_card":false},{"app_id":1579977751,"name":"Idle Mine RPG","publisher_id":"1281721366","publisher_name":"Iron Horse Games LLC","categories":[6014,7014,7015],"subtitle":null,"icon_url":"https://is5-ssl.mzstatic.com/image/thumb/Purple125/v4/f9/2c/40/f92c4044-f596-4ffe-fafc-0e33496865c8/AppIcon-0-0-1x_U007emarketing-0-0-0-7-0-0-sRGB-0-0-0-GLES2_U002c0-512MB-85-220-0-0.png/1024x1024bb.png","offer":{"action_text":"LADEN","price":0,"price_formatted":"0,00 €"},"on_card":false},{"app_id":1116645064,"name":"Idle Miner Tycoon: Gold Rush","publisher_id":"1112983227","publisher_name":"Kolibri Games GmbH","categories":[6014,7015,7017,6016],"subtitle":"Aufbau & Geld Strategie Spiele","icon_url":"https://is5-ssl.mzstatic.com/image/thumb/Purple122/v4/7b/d1/11/7bd111a7-5dd3-95d2-fe5d-93e582ae05c4/AppIcon-0-0-1x_U007emarketing-0-0-0-7-0-0-sRGB-0-0-0-GLES2_U002c0-512MB-85-220-0-0.png/1024x1024bb.png","offer":{"action_text":"LADEN","price":0,"price_formatted":"0,00 €"},"on_card":false},{"app_id":1516587337,"name":"Game of Nations: Idle RPG","publisher_id":"573159769","publisher_name":"eRepublik Labs","categories":[6014,7017,7014,6016],"subtitle":"Helden folgen deinem Befehl!","icon_url":"https://is1-ssl.mzstatic.com/image/thumb/Purple122/v4/ba/56/08/ba5608fd-70e7-df0b-5557-355261012f75/AppIcon-0-0-1x_U007emarketing-0-0-0-7-0-0-sRGB-0-0-0-GLES2_U002c0-512MB-85-220-0-0.png/1024x1024bb.png","offer":{"action_text":"LADEN","price":0,"price_formatted":"0,00 €"},"on_card":false},{"app_id":1413287364,"name":"Redecor - Home Design Makeover","publisher_id":"1413287363","publisher_name":"Reworks","categories":[6014,6012,7015],"subtitle":"Sharpen your decorating skills","icon_url":"https://is3-ssl.mzstatic.com/image/thumb/Purple112/v4/00/32/34/003234d8-605e-deb4-6553-5bd5233e6360/AppIcon-0-0-1x_U007emarketing-0-0-0-7-0-0-sRGB-0-0-0-GLES2_U002c0-512MB-85-220-0-0.png/1024x1024bb.png","offer":{"action_text":"LADEN","price":0,"price_formatted":"0,00 €"},"on_card":false},{"app_id":1068366937,"name":"Tap Tap Fish - AbyssRium","publisher_id":"896208121","publisher_name":"SangHeon Kim","categories":[6014,7015,6017,7017],"subtitle":null,"icon_url":"https://is2-ssl.mzstatic.com/image/thumb/Purple112/v4/2f/76/dc/2f76dc8d-2e36-49ab-c4f3-7dd46eed96be/AppIcon-0-0-1x_U007emarketing-0-0-0-7-0-0-sRGB-0-0-0-GLES2_U002c0-512MB-85-220-0-0.png/1024x1024bb.png","offer":{"action_text":"LADEN","price":0,"price_formatted":"0,00 €"},"on_card":false},{"app_id":1553029497,"name":"Day Repeat Day","publisher_id":"491318781","publisher_name":"Kimmo Factor Oy","categories":[6014,7003,7012],"subtitle":null,"icon_url":"https://is3-ssl.mzstatic.com/image/thumb/Purple126/v4/53/2c/c1/532cc1d1-b826-3b3f-1aa0-13b40344c749/AppIcon-0-0-1x_U007emarketing-0-0-0-7-0-0-sRGB-0-0-0-GLES2_U002c0-512MB-85-220-0-0.png/1024x1024bb.png","offer":{"action_text":"KAUFEN","price":499,"price_formatted":"4,99 €"},"on_card":false},{"app_id":1585729056,"name":"The Office: Somehow We Manage","publisher_id":"498050264","publisher_name":"Eastside Games","categories":[6014,7015,7003],"subtitle":null,"icon_url":"https://is4-ssl.mzstatic.com/image/thumb/Purple112/v4/6f/21/20/6f2120e3-337d-1980-9607-aeaf36068da8/AppIcon-0-0-1x_U007emarketing-0-0-0-7-0-0-sRGB-0-0-0-GLES2_U002c0-512MB-85-220-0-0.png/1024x1024bb.png","offer":{"action_text":"LADEN","price":0,"price_formatted":"0,00 €"},"on_card":false}],"substyle":null},{"position":4,"id":"1588878548","url":"https://apps.apple.com/de/story/id1588878548","title":"Diese Woche angesagt","label":"IM TREND","short_description":"Diese Apps liegen diese Woche im Trend","style":"content","artwork":null,"video_preview_url":null,"apps":[{"app_id":1586366816,"name":"Dream by WOMBO","publisher_id":"1531396122","publisher_name":"Wombo Studios, Inc.","categories":[6027,6016],"subtitle":null,"icon_url":"https://is3-ssl.mzstatic.com/image/thumb/Purple112/v4/1b/f7/f3/1bf7f34e-b595-d397-be09-0e0060ce7d66/AppIcon-1x_U007emarketing-0-10-0-85-220.png/1024x1024bb.png","offer":{"action_text":"LADEN","price":0,"price_formatted":"0,00 €"},"on_card":true},{"app_id":1552153525,"name":"Idle Lumber Empire","publisher_id":"1574181686","publisher_name":"Game Veterans","categories":[6014,6016,7015,7017],"subtitle":"Werde zum aufbau holz empire","icon_url":"https://is5-ssl.mzstatic.com/image/thumb/Purple116/v4/46/cc/f7/46ccf760-1db5-fe77-f6ea-e81fbc2d7d82/AppIcon-0-0-1x_U007emarketing-0-0-0-7-0-0-sRGB-0-0-0-GLES2_U002c0-512MB-85-220-0-0.png/1024x1024bb.png","offer":{"action_text":"LADEN","price":0,"price_formatted":"0,00 €"},"on_card":true},{"app_id":1252497129,"name":"PictureThis-Pflanzen Bestimmen","publisher_id":"1499301607","publisher_name":"Glority Global Group Ltd.","categories":[6017,6012],"subtitle":"Blumen Bäume Blätter Erkennen","icon_url":"https://is4-ssl.mzstatic.com/image/thumb/Purple112/v4/da/2c/34/da2c3494-85a6-efbd-7c5f-03cc5689a3c1/AppIcon-0-1x_U007emarketing-0-7-0-85-220.png/1024x1024bb.png","offer":{"action_text":"LADEN","price":0,"price_formatted":"0,00 €"},"on_card":true},{"app_id":1094591345,"name":"Pokémon GO","publisher_id":"1037205060","publisher_name":"Niantic, Inc.","categories":[6014,7017,7014,6013],"subtitle":"Suche weltweit Pokémon","icon_url":"https://is3-ssl.mzstatic.com/image/thumb/Purple122/v4/d4/38/b2/d438b2b1-dabd-614c-a476-ed148600b08b/AppIcon-1x_U007emarketing-0-7-0-85-220.png/1024x1024bb.png","offer":{"action_text":"LADEN","price":0,"price_formatted":"0,00 €"},"on_card":true},{"app_id":1057991212,"name":"RTL+","publisher_id":"310266588","publisher_name":"RTL interactive","categories":[6016,6012],"subtitle":"Live TV, Serien, Shows & Filme","icon_url":"https://is5-ssl.mzstatic.com/image/thumb/Purple112/v4/ba/9e/e7/ba9ee757-b923-755a-d3cd-45cdeacff3ca/AppIcon-0-0-1x_U007emarketing-0-0-0-7-0-0-sRGB-0-0-0-GLES2_U002c0-512MB-85-220-0-0.png/1024x1024bb.png","offer":{"action_text":"LADEN","price":0,"price_formatted":"0,00 €"},"on_card":true},{"app_id":512939461,"name":"Subway Surfers","publisher_id":"471259040","publisher_name":"Sybo Games ApS","categories":[6014,7001,7003,6016],"subtitle":"Erlebe endlosen Laufspaß!","icon_url":"https://is2-ssl.mzstatic.com/image/thumb/Purple112/v4/1c/ff/c3/1cffc347-2075-2275-60a0-e9c8a6b7c064/AppIcon-0-0-1x_U007emarketing-0-0-0-7-0-0-sRGB-0-0-0-GLES2_U002c0-512MB-85-220-0-0.png/1024x1024bb.png","offer":{"action_text":"LADEN","price":0,"price_formatted":"0,00 €"},"on_card":true},{"app_id":447374873,"name":"Komoot: Radtouren & Wanderwege","publisher_id":"365019076","publisher_name":"komoot GmbH","categories":[6013,6010],"subtitle":"Routenplaner, Karten & GPS","icon_url":"https://is2-ssl.mzstatic.com/image/thumb/Purple126/v4/65/c6/90/65c690c6-4f88-feef-de6c-5324748cc52f/AppIcon-1x_U007emarketing-0-7-0-85-220.png/1024x1024bb.png","offer":{"action_text":"LADEN","price":0,"price_formatted":"0,00 €"},"on_card":true},{"app_id":1116645064,"name":"Idle Miner Tycoon: Gold Rush","publisher_id":"1112983227","publisher_name":"Kolibri Games GmbH","categories":[6014,7015,7017,6016],"subtitle":"Aufbau & Geld Strategie Spiele","icon_url":"https://is5-ssl.mzstatic.com/image/thumb/Purple122/v4/7b/d1/11/7bd111a7-5dd3-95d2-fe5d-93e582ae05c4/AppIcon-0-0-1x_U007emarketing-0-0-0-7-0-0-sRGB-0-0-0-GLES2_U002c0-512MB-85-220-0-0.png/1024x1024bb.png","offer":{"action_text":"LADEN","price":0,"price_formatted":"0,00 €"},"on_card":true},{"app_id":1476035637,"name":"Applaydu Spiele für Familien","publisher_id":"516512633","publisher_name":"FERRERO TRADING LUX S.A.","categories":[6017,6014,7009,7002],"subtitle":"Aktivitäten für Ihre Kinder","icon_url":"https://is1-ssl.mzstatic.com/image/thumb/Purple116/v4/02/25/e2/0225e220-68e3-ecf3-d86e-37bd3c48aa3f/AppIcon-0-0-1x_U007emarketing-0-0-0-7-0-0-sRGB-0-0-0-GLES2_U002c0-512MB-85-220-0-0.png/1024x1024bb.png","offer":{"action_text":"LADEN","price":0,"price_formatted":"0,00 €"},"on_card":true},{"app_id":1515796612,"name":"Moises: Die Musiker-App","publisher_id":"1515796611","publisher_name":"Moises Systems, Inc","categories":[6011,6007],"subtitle":"Gesang/Instrumente entfernen","icon_url":"https://is3-ssl.mzstatic.com/image/thumb/Purple112/v4/db/6e/14/db6e14b7-703d-bec2-946c-81f9da87a06f/AppIcon-0-0-1x_U007emarketing-0-0-0-10-0-0-sRGB-0-0-0-GLES2_U002c0-512MB-85-220-0-0.png/1024x1024bb.png","offer":{"action_text":"LADEN","price":0,"price_formatted":"0,00 €"},"on_card":true},{"app_id":549105915,"name":"True Skate","publisher_id":"337866373","publisher_name":"True Axis","categories":[6014,6016,7016,7001],"subtitle":null,"icon_url":"https://is1-ssl.mzstatic.com/image/thumb/Purple112/v4/e9/f2/df/e9f2dfbb-4b63-5561-a65c-ad003e32f25d/AppIcon-1x_U007emarketing-0-4-85-220.png/1024x1024bb.png","offer":{"action_text":"KAUFEN","price":199,"price_formatted":"1,99 €"},"on_card":true},{"app_id":625994547,"name":"Eurovision Song Contest","publisher_id":"625994570","publisher_name":"digame GmbH","categories":[6016,6011],"subtitle":"The Official App","icon_url":"https://is1-ssl.mzstatic.com/image/thumb/Purple116/v4/b1/4c/8d/b14c8d6b-38f9-1f5f-e15a-09ffe333b4fd/AppIcon-1x_U007emarketing-0-7-0-85-220.png/1024x1024bb.png","offer":{"action_text":"LADEN","price":0,"price_formatted":"0,00 €"},"on_card":true},{"app_id":911121200,"name":"Good Pizza, Great Pizza","publisher_id":"1055223695","publisher_name":"TAPBLAZE","categories":[6014,7015,6023,7003],"subtitle":"Pizzeria-Simulator","icon_url":"https://is1-ssl.mzstatic.com/image/thumb/Purple122/v4/3c/9b/3c/3c9b3c8d-9a24-78b6-45d0-1fc14b89586f/AppIcon-1x_U007emarketing-0-7-0-85-220.png/1024x1024bb.png","offer":{"action_text":"LADEN","price":0,"price_formatted":"0,00 €"},"on_card":true},{"app_id":1129523589,"name":"DAZN Sport Live Stream","publisher_id":"1085544656","publisher_name":"DAZN Limited","categories":[6004,6016],"subtitle":"Fußball, NFL, NBA & mehr","icon_url":"https://is5-ssl.mzstatic.com/image/thumb/Purple126/v4/b8/25/bb/b825bb81-ce2a-da02-af4f-46778bc9d191/AppIcon-0-0-1x_U007emarketing-0-0-0-7-0-0-sRGB-0-0-0-GLES2_U002c0-512MB-85-220-0-0.png/1024x1024bb.png","offer":{"action_text":"LADEN","price":0,"price_formatted":"0,00 €"},"on_card":true},{"app_id":1489732936,"name":"Sherlock: Suchspiele・3 Gewinnt","publisher_id":"305426797","publisher_name":"G5 Entertainment AB","categories":[6014,7002,7012,6016],"subtitle":"Wimmelbildspiele: Abenteuer","icon_url":"https://is1-ssl.mzstatic.com/image/thumb/Purple122/v4/4d/2b/a5/4d2ba5d8-787a-adb2-f1e3-26295ef2bd78/AppIcon-0-0-1x_U007emarketing-0-0-0-7-0-0-sRGB-0-0-0-GLES2_U002c0-512MB-85-220-0-0.png/1024x1024bb.png","offer":{"action_text":"LADEN","price":0,"price_formatted":"0,00 €"},"on_card":true},{"app_id":1500855883,"name":"CapCut - Video Editor","publisher_id":"1497663561","publisher_name":"Bytedance Pte. Ltd","categories":[6008],"subtitle":null,"icon_url":"https://is3-ssl.mzstatic.com/image/thumb/Purple116/v4/ed/10/57/ed10575a-83c7-126f-bcbc-8ecb909791a6/AppIcon-0-0-1x_U007emarketing-0-0-0-7-0-0-sRGB-0-0-0-GLES2_U002c0-512MB-85-220-0-0.png/1024x1024bb.png","offer":{"action_text":"LADEN","price":0,"price_formatted":"0,00 €"},"on_card":true},{"app_id":529479190,"name":"Clash of Clans","publisher_id":"488106216","publisher_name":"Supercell","categories":[6014,7001,6016,7017],"subtitle":"Führe deinen Clan zum Sieg!","icon_url":"https://is4-ssl.mzstatic.com/image/thumb/Purple112/v4/f2/97/5e/f2975e30-a197-7ea5-36b2-eca041f4be89/AppIcon-0-0-1x_U007emarketing-0-0-0-6-0-0-sRGB-0-0-0-GLES2_U002c0-512MB-85-220-0-0.png/1024x1024bb.png","offer":{"action_text":"LADEN","price":0,"price_formatted":"0,00 €"},"on_card":true}],"substyle":"list"},{"position":5,"id":"1498410977","url":"https://apps.apple.com/de/story/id1498410977","title":"Setz deine Fotos in Szene","label":"APP\nDES\nTAGES","short_description":"Mit PhotoRoom verleihst du Hintergründen das gewisse Etwas.","style":"branded","artwork":{"url":"https://is5-ssl.mzstatic.com/image/thumb/Features113/v4/ec/63/68/ec6368a1-94b5-5e71-69b5-72b21e3935e6/source/3524x2160bb.png","text_colors":["fce60f","e6e595","cfcc2c","bdcb98"],"bg_color":"1a66a1","alpha":false},"video_preview_url":null,"apps":[{"app_id":1455009060,"name":"PhotoRoom Studio Photo Editor","publisher_id":"1477313433","publisher_name":"ARTIZANS OF PHOTO VIDEO BACKGROUND EDITOR APP","categories":[6027,6008],"subtitle":"Foto & Weißer Hintergrund","icon_url":"https://is4-ssl.mzstatic.com/image/thumb/Purple112/v4/31/13/31/31133157-0b03-ad5c-e863-7617b8793c74/AppIcon-0-0-1x_U007emarketing-0-7-0-sRGB-0-85-220-0.png/1024x1024bb.png","offer":{"action_text":"LADEN","price":0,"price_formatted":"0,00 €"},"on_card":true}],"substyle":"app_of_day"},{"position":6,"id":"1302421762","url":"https://apps.apple.com/de/story/id1302421762","title":"Sonic Forces","label":"SPIEL\nDES\nTAGES","short_description":"Dehnen nicht vergessen! Es wird schnell, sehr schnell.","style":"branded","artwork":{"url":"https://is1-ssl.mzstatic.com/image/thumb/Features118/v4/59/3f/e8/593fe874-8a79-a6e2-3381-f0e5c62007c1/source/3524x2160bb.png","text_colors":["000000","000000","000000","000000"],"bg_color":"000000","alpha":false},"video_preview_url":null,"apps":[{"app_id":1262362476,"name":"Sonic Forces - Rennen spiele","publisher_id":"281966698","publisher_name":"SEGA","categories":[6014,6016,7001,7003],"subtitle":"Rennspiele und Laufspiele","icon_url":"https://is5-ssl.mzstatic.com/image/thumb/Purple112/v4/19/ea/b2/19eab27f-c59b-6972-ac1a-ff26dac05bc2/AppIcon-0-0-1x_U007emarketing-0-0-0-7-0-0-sRGB-0-0-0-GLES2_U002c0-512MB-85-220-0-0.png/1024x1024bb.png","offer":{"action_text":"LADEN","price":0,"price_formatted":"0,00 €"},"on_card":true}],"substyle":"game_of_day"}]}