{"country":"FR","date":"2021-10-08T00:00:00Z","stories":[{"position":1,"id":"1585360758","url":"https://apps.apple.com/fr/story/id1585360758","title":"Vivez l’aventure de Daï","label":"NOUVEAU JEU","short_description":null,"style":"content","artwork":{"url":"https://is5-ssl.mzstatic.com/image/thumb/Features115/v4/8a/e8/6e/8ae86e1e-5ac9-3da4-656f-b256e1917099/source/3524x2160bb.png","text_colors":["ffffff","ffffff","c3ccf3","c9bac4"],"bg_color":"0047eb","alpha":false},"video_preview_url":null,"apps":[{"app_id":1542879571,"name":"DQ Dai: A Hero’s Bonds","publisher_id":"300186801","publisher_name":"SQUARE ENIX","categories":[6014,7014,7001],"subtitle":"RPG d'action en équipe","icon_url":"https://is5-ssl.mzstatic.com/image/thumb/Purple125/v4/1c/91/de/1c91de7f-0ae2-7008-2a08-aaf4cd769952/AppIcon-0-0-1x_U007emarketing-0-0-0-7-0-0-sRGB-0-0-0-GLES2_U002c0-512MB-85-220-0-0.png/1024x1024bb.png","offer":{"action_text":"OBTENIR","price":0,"price_formatted":"0,00 €"},"on_card":true}],"substyle":"editorial"},{"position":2,"id":"1492287158","url":"https://apps.apple.com/fr/story/id1492287158","title":"Nos jeux du moment 🔥","label":"NOS FAVORIS","short_description":null,"style":"content","artwork":null,"video_preview_url":null,"apps":[{"app_id":1512321575,"name":"Pokémon UNITE","publisher_id":"446737235","publisher_name":"The Pokemon Company","categories":[6014,7017,7001],"subtitle":null,"icon_url":"https://is1-ssl.mzstatic.com/image/thumb/Purple115/v4/94/ee/bd/94eebdf0-07b1-402c-707f-dff8e5c0c72b/AppIcon-0-0-1x_U007emarketing-0-0-0-7-0-0-sRGB-0-0-0-GLES2_U002c0-512MB-85-220-0-0.png/1024x1024bb.png","offer":{"action_text":"OBTENIR","price":0,"price_formatted":"0,00 €"},"on_card":true},{"app_id":1485854536,"name":"Le Seigneur des Anneaux: Appel","publisher_id":"1485225410","publisher_name":"NETEASE INTERACTIVE ENTERTAINMENT PTE. LTD","categories":[6014,7015,7017],"subtitle":"Un anneau pour les gouverner","icon_url":"https://is5-ssl.mzstatic.com/image/thumb/Purple125/v4/80/01/4a/80014aaa-40db-7fd5-8412-6e14265eeaf6/AppIcon-0-0-1x_U007emarketing-0-0-0-10-0-0-sRGB-0-0-0-GLES2_U002c0-512MB-85-220-0-0.png/1024x1024bb.png","offer":{"action_text":"OBTENIR","price":0,"price_formatted":"0,00 €"},"on_card":true},{"app_id":1351168404,"name":"Among Us!","publisher_id":"957995279","publisher_name":"InnerSloth LLC","categories":[6014,7001,7015],"subtitle":null,"icon_url":"https://is5-ssl.mzstatic.com/image/thumb/Purple115/v4/7e/b6/3d/7eb63dbd-58d0-698e-9cfb-db98e7211537/AppIcon-1x_U007emarketing-0-7-0-85-220.png/1024x1024bb.png","offer":{"action_text":"OBTENIR","price":0,"price_formatted":"0,00 €"},"on_card":true},{"app_id":1466943149,"name":"GWENT: The Witcher Card Game","publisher_id":"509542878","publisher_name":"CD PROJEKT S.A.","categories":[6014,7005],"subtitle":"Batailles de Cartes Épiques","icon_url":"https://is5-ssl.mzstatic.com/image/thumb/Purple125/v4/58/52/58/58525834-408f-caf4-7dad-31fd53bc7b2d/AppIcon-1x_U007emarketing-0-7-0-85-220.png/1024x1024bb.png","offer":{"action_text":"OBTENIR","price":0,"price_formatted":"0,00 €"},"on_card":true},{"app_id":1480191929,"name":"Pocket Styler: Fashion Stars","publisher_id":"348389028","publisher_name":"Nordcurrent UAB","categories":[6014,6012,7015,7003],"subtitle":"Your fashion story starts NOW!","icon_url":"https://is5-ssl.mzstatic.com/image/thumb/Purple125/v4/4f/cf/b1/4fcfb158-4e47-5fcb-f56d-c86107472644/AppIcon-0-0-1x_U007emarketing-0-0-0-7-0-0-sRGB-0-0-0-GLES2_U002c0-512MB-85-220-0-0.png/1024x1024bb.png","offer":{"action_text":"OBTENIR","price":0,"price_formatted":"0,00 €"},"on_card":true},{"app_id":1293634699,"name":"Mario Kart Tour","publisher_id":"1062496488","publisher_name":"Nintendo Co., Ltd.","categories":[6014,7001,7013],"subtitle":"Race around the world!","icon_url":"https://is3-ssl.mzstatic.com/image/thumb/Purple115/v4/41/78/bb/4178bb95-8695-c182-814b-9f271cfc2411/AppIcon-0-0-1x_U007emarketing-0-0-0-7-0-0-sRGB-0-0-0-GLES2_U002c0-512MB-85-220-0-0.png/1024x1024bb.png","offer":{"action_text":"OBTENIR","price":0,"price_formatted":"0,00 €"},"on_card":true},{"app_id":431946152,"name":"ROBLOX","publisher_id":"431946155","publisher_name":"Roblox Corporation","categories":[6014,7002,7001,6016],"subtitle":null,"icon_url":"https://is3-ssl.mzstatic.com/image/thumb/Purple115/v4/0d/42/ac/0d42ace2-9139-c172-e414-91ae73beca3f/AppIcon-1x_U007emarketing-0-7-0-0-85-220.png/1024x1024bb.png","offer":{"action_text":"OBTENIR","price":0,"price_formatted":"0,00 €"},"on_card":true},{"app_id":1465097065,"name":"Infinite Galaxy","publisher_id":"1300436103","publisher_name":"CAMEL GAMES LIMITED","categories":[6014,7017,7015],"subtitle":"Commandez la flotte spatiale!","icon_url":"https://is3-ssl.mzstatic.com/image/thumb/Purple125/v4/e3/5d/0b/e35d0b44-67a7-9894-45b5-494e0c766429/AppIcon-0-0-1x_U007emarketing-0-0-0-7-0-0-sRGB-0-0-0-GLES2_U002c0-512MB-85-220-0-0.png/1024x1024bb.png","offer":{"action_text":"OBTENIR","price":0,"price_formatted":"0,00 €"},"on_card":true},{"app_id":1456213261,"name":"Mobile Legends: Adventure","publisher_id":"910435102","publisher_name":"Shanghai Moonton Technology Co., Ltd.","categories":[6014,7017,7014],"subtitle":"un nouveau début de l'aventure","icon_url":"https://is3-ssl.mzstatic.com/image/thumb/Purple115/v4/be/a5/0d/bea50db3-e49c-e6f1-db23-e7cb8dc90583/AppIcon-0-0-1x_U007emarketing-0-0-0-9-0-0-sRGB-0-0-0-GLES2_U002c0-512MB-85-220-0-0.png/1024x1024bb.png","offer":{"action_text":"OBTENIR","price":0,"price_formatted":"0,00 €"},"on_card":true},{"app_id":1053012308,"name":"Clash Royale","publisher_id":"488106216","publisher_name":"Supercell","categories":[6014,7017,6016,7001],"subtitle":"Combats JcJ épiques !","icon_url":"https://is2-ssl.mzstatic.com/image/thumb/Purple115/v4/b3/ab/36/b3ab36da-6110-fca6-dc23-a260c3a9f0a7/AppIcon-1x_U007emarketing-6-0-85-220.png/1024x1024bb.png","offer":{"action_text":"OBTENIR","price":0,"price_formatted":"0,00 €"},"on_card":true},{"app_id":512939461,"name":"Subway Surfers","publisher_id":"471259040","publisher_name":"Sybo Games ApS","categories":[6014,7001,7003,6016],"subtitle":"Rejoignez la course infinie!","icon_url":"https://is2-ssl.mzstatic.com/image/thumb/Purple115/v4/4c/ae/96/4cae96d1-5e2a-0d72-7c84-e9633ff1bb3e/AppIcon-0-0-1x_U007emarketing-0-0-0-7-0-0-sRGB-0-0-0-GLES2_U002c0-512MB-85-220-0-0.png/1024x1024bb.png","offer":{"action_text":"OBTENIR","price":0,"price_formatted":"0,00 €"},"on_card":true},{"app_id":1287282214,"name":"Call of Duty®: Mobile","publisher_id":"285005466","publisher_name":"Activision Publishing, Inc.","categories":[6014,7001],"subtitle":"Battle Royale, Sniper","icon_url":"https://is1-ssl.mzstatic.com/image/thumb/Purple125/v4/05/2a/2b/052a2bde-a4fd-c763-d852-5a7e87aa2463/AppIcon-1x_U007emarketing-0-9-0-85-220.png/1024x1024bb.png","offer":{"action_text":"OBTENIR","price":0,"price_formatted":"0,00 €"},"on_card":true},{"app_id":1553900372,"name":"Truck Simulator : Ultimate","publisher_id":"973445339","publisher_name":"Zuuks Games","categories":[6014,7015],"subtitle":null,"icon_url":"https://is3-ssl.mzstatic.com/image/thumb/Purple115/v4/7b/d0/b4/7bd0b48f-ee9e-7282-210d-672fa56a6410/AppIcon-1x_U007emarketing-0-7-0-85-220.png/1024x1024bb.png","offer":{"action_text":"OBTENIR","price":0,"price_formatted":"0,00 €"},"on_card":true},{"app_id":1500251668,"name":"Solitaire Cruise Tripeaks Jeux","publisher_id":"1143580778","publisher_name":"Samfinaco Limited","categories":[6014,7005,7012,6016],"subtitle":"Le jeu de cartes solitario","icon_url":"https://is4-ssl.mzstatic.com/image/thumb/Purple115/v4/f5/e7/de/f5e7decd-dcdd-0c55-b88d-931f769e0e99/AppIcon-0-0-1x_U007emarketing-0-0-0-7-0-0-sRGB-0-0-0-GLES2_U002c0-512MB-85-220-0-0.png/1024x1024bb.png","offer":{"action_text":"OBTENIR","price":0,"price_formatted":"0,00 €"},"on_card":true},{"app_id":1094930513,"name":"FIFA Football","publisher_id":"284800461","publisher_name":"Electronic Arts","categories":[6014,7016,7015],"subtitle":"Formez votre équipe de rêve.","icon_url":"https://is3-ssl.mzstatic.com/image/thumb/Purple115/v4/ce/86/78/ce8678c8-0172-bcc2-2650-9b7d0c68aeb6/AppIcon-0-0-1x_U007emarketing-0-0-0-7-0-0-sRGB-0-0-0-GLES2_U002c0-512MB-85-220-0-0.png/1024x1024bb.png","offer":{"action_text":"OBTENIR","price":0,"price_formatted":"0,00 €"},"on_card":true},{"app_id":1300146617,"name":"Garena Free Fire - Fête Booyah","publisher_id":"1335627134","publisher_name":"GARENA INTERNATIONAL I PRIVATE LIMITED","categories":[6014,7001,7002],"subtitle":"10-minutes, Sniper Survivant!","icon_url":"https://is1-ssl.mzstatic.com/image/thumb/Purple115/v4/c0/8e/5d/c08e5d2a-8638-d844-27b5-e5536ac96a24/AppIcon-1631895036-1x_U007emarketing-0-7-0-85-220.png/1024x1024bb.png","offer":{"action_text":"OBTENIR","price":0,"price_formatted":"0,00 €"},"on_card":true},{"app_id":1484442152,"name":"Merge Mansion","publisher_id":"974585521","publisher_name":"Metacore Games Oy","categories":[6014,7012],"subtitle":"Mansion full of mysteries!","icon_url":"https://is1-ssl.mzstatic.com/image/thumb/Purple125/v4/21/21/d7/2121d7a3-7dfc-5a25-eaf7-cad8be73e1f7/AppIcon-0-0-1x_U007emarketing-0-0-0-7-0-0-sRGB-0-0-0-GLES2_U002c0-512MB-85-220-0-0.png/1024x1024bb.png","offer":{"action_text":"OBTENIR","price":0,"price_formatted":"0,00 €"},"on_card":true},{"app_id":1314391359,"name":"FRAG Pro Shooter","publisher_id":"547556985","publisher_name":"Oh BiBi","categories":[6014,7003,7001],"subtitle":"ON SE CACHE PLUS, ON FRAG!","icon_url":"https://is5-ssl.mzstatic.com/image/thumb/Purple125/v4/25/48/e8/2548e8e9-2900-c64f-99fc-13e4182c8c10/AppIcon-0-0-1x_U007emarketing-0-0-0-7-0-0-sRGB-0-0-0-GLES2_U002c0-512MB-85-220-0-0.png/1024x1024bb.png","offer":{"action_text":"OBTENIR","price":0,"price_formatted":"0,00 €"},"on_card":true},{"app_id":1222489978,"name":"Airplane Chefs: Jeu de Cuisine","publisher_id":"348389028","publisher_name":"Nordcurrent UAB","categories":[6014,7001,6016,7003],"subtitle":"Le chef du ciel, c'est vous !","icon_url":"https://is3-ssl.mzstatic.com/image/thumb/Purple115/v4/82/f5/14/82f514f4-89bd-88b0-8b22-0ad359857416/AppIcon-0-0-1x_U007emarketing-0-0-0-7-0-0-sRGB-0-0-0-GLES2_U002c0-512MB-85-220-0-0.png/1024x1024bb.png","offer":{"action_text":"OBTENIR","price":0,"price_formatted":"0,00 €"},"on_card":true},{"app_id":1453707997,"name":"Flying Flogger","publisher_id":"1453707996","publisher_name":"Asot Calasean","categories":[6014,7001],"subtitle":null,"icon_url":"https://is4-ssl.mzstatic.com/image/thumb/Purple125/v4/d1/bb/69/d1bb6953-f83e-55ef-af27-9303eb9f320b/AppIcon-1x_U007emarketing-0-0-GLES2_U002c0-512MB-sRGB-0-0-0-85-220-0-0-0-8.png/1024x1024bb.png","offer":{"action_text":"Acheter","price":99,"price_formatted":"0,99 €"},"on_card":true}],"substyle":"list"},{"position":3,"id":"1576157774","url":"https://apps.apple.com/fr/story/id1576157774","title":"Aidez vos enfants à apprendre","label":"BIEN DÉMARRER","short_description":"","style":"content","artwork":{"url":"https://is2-ssl.mzstatic.com/image/thumb/Features125/v4/e5/ee/8a/e5ee8aeb-6791-caed-0292-f801ad9bed03/source/3524x2160bb.png","text_colors":["14120e","15130b","142922","142a1f"],"bg_color":"1aa590","alpha":false},"video_preview_url":null,"apps":[{"app_id":1138436619,"name":"La Maternelle Montessori","publisher_id":"555989645","publisher_name":"EDOKI ACADEMY","categories":[6017],"subtitle":"Apprendre à lire et à compter","icon_url":"https://is4-ssl.mzstatic.com/image/thumb/Purple125/v4/0e/0b/43/0e0b43b8-9d73-8f56-ed01-b3c31eed577d/AppIcon-0-0-1x_U007emarketing-0-0-0-7-0-0-sRGB-0-0-0-GLES2_U002c0-512MB-85-220-0-0.png/1024x1024bb.png","offer":{"action_text":"OBTENIR","price":0,"price_formatted":"0,00 €"},"on_card":true}],"substyle":"editorial"},{"position":4,"id":"1568065160","url":"https://apps.apple.com/fr/story/id1568065160","title":"Essayez ces apps de streaming","label":"RECOMMANDÉ","short_description":null,"style":"content","artwork":null,"video_preview_url":null,"apps":[{"app_id":667935767,"name":"ADN - Anime Digital Network","publisher_id":"431104866","publisher_name":"VIZ Media Europe","categories":[6016],"subtitle":"Au cœur de l'animation","icon_url":"https://is1-ssl.mzstatic.com/image/thumb/Purple115/v4/ab/90/1b/ab901b11-5866-3058-4be7-a39d1554e82e/AppIcon-0-0-1x_U007emarketing-0-0-0-7-0-0-sRGB-0-0-0-GLES2_U002c0-512MB-85-220-0-0.png/1024x1024bb.png","offer":{"action_text":"OBTENIR","price":0,"price_formatted":"0,00 €"},"on_card":true},{"app_id":1129523589,"name":"DAZN: Live Sports Streaming","publisher_id":"1085544656","publisher_name":"DAZN Limited","categories":[6004,6016],"subtitle":"Watch Boxing Live","icon_url":"https://is4-ssl.mzstatic.com/image/thumb/Purple115/v4/50/9a/79/509a793c-8bfd-1ac1-b5a6-141e9aa0f4dd/AppIcon-0-0-1x_U007emarketing-0-0-0-7-0-0-sRGB-0-0-0-GLES2_U002c0-512MB-85-220-0-0.png/1024x1024bb.png","offer":{"action_text":"OBTENIR","price":0,"price_formatted":"0,00 €"},"on_card":true},{"app_id":544007664,"name":"YouTube","publisher_id":"281956209","publisher_name":"Google LLC","categories":[6008,6016],"subtitle":"Musique & Vidéos à regarder","icon_url":"https://is2-ssl.mzstatic.com/image/thumb/Purple115/v4/58/6a/90/586a906f-6e51-e93e-6e9b-5ed2682bfef6/logo_youtube_color-0-0-1x_U007emarketing-0-0-0-6-0-0-sRGB-0-0-0-GLES2_U002c0-512MB-85-220-0-0.png/1024x1024bb.png","offer":{"action_text":"OBTENIR","price":0,"price_formatted":"0,00 €"},"on_card":true},{"app_id":689165391,"name":"Hopster: Dessins Animés, Jeux","publisher_id":"689165394","publisher_name":"Hopster","categories":[6017,6014,7009],"subtitle":"TV, Music, Jeux pour Enfants","icon_url":"https://is1-ssl.mzstatic.com/image/thumb/Purple125/v4/54/3f/2f/543f2f22-4a22-f6cc-8be5-efab87274a2b/AppIcon-1x_U007emarketing-0-4-0-0-85-220.png/1024x1024bb.png","offer":{"action_text":"OBTENIR","price":0,"price_formatted":"0,00 €"},"on_card":true},{"app_id":626148774,"name":"MUBI: Le Choix du Cinéma","publisher_id":"626148777","publisher_name":"MUBI, Inc.","categories":[6016,6008],"subtitle":"Regardez du grand cinéma","icon_url":"https://is1-ssl.mzstatic.com/image/thumb/Purple125/v4/0e/0d/53/0e0d539f-e657-83f6-fd8e-e20492f41781/AppIcon-0-0-1x_U007emarketing-0-0-0-7-0-0-sRGB-0-0-0-GLES2_U002c0-512MB-85-220-0-0.png/1024x1024bb.png","offer":{"action_text":"OBTENIR","price":0,"price_formatted":"0,00 €"},"on_card":true},{"app_id":1446075923,"name":"Disney+","publisher_id":"284888248","publisher_name":"Disney","categories":[6016],"subtitle":"Un divertissement en continu","icon_url":"https://is1-ssl.mzstatic.com/image/thumb/Purple115/v4/eb/1b/bd/eb1bbdd3-2151-2a4f-2b4f-4f14ec578650/AppIcon-0-0-1x_U007emarketing-0-0-0-7-0-0-sRGB-0-0-0-GLES2_U002c0-512MB-85-220-0-0.png/1024x1024bb.png","offer":{"action_text":"OBTENIR","price":0,"price_formatted":"0,00 €"},"on_card":true},{"app_id":694580816,"name":"myCANAL","publisher_id":"694580819","publisher_name":"GROUPE CANAL+","categories":[6016],"subtitle":"Votre TV en live ou en replay","icon_url":"https://is5-ssl.mzstatic.com/image/thumb/Purple115/v4/b5/2c/b4/b52cb412-b574-8755-79ce-7f29f5efcfcd/CPAppIcon-0-0-1x_U007emarketing-0-0-0-6-0-0-sRGB-0-0-0-GLES2_U002c0-512MB-85-220-0-0.png/1024x1024bb.png","offer":{"action_text":"OBTENIR","price":0,"price_formatted":"0,00 €"},"on_card":true},{"app_id":1112438268,"name":"RMC Sport – Live TV, Replay","publisher_id":"309172115","publisher_name":"SFR","categories":[6004],"subtitle":"Champions League, MMA en live","icon_url":"https://is2-ssl.mzstatic.com/image/thumb/Purple125/v4/7c/e5/92/7ce59268-c0f7-7b5d-9583-580a181c917f/AppIcon-0-0-1x_U007emarketing-0-0-0-7-0-0-sRGB-0-0-0-GLES2_U002c0-512MB-85-220-0-0.png/1024x1024bb.png","offer":{"action_text":"OBTENIR","price":0,"price_formatted":"0,00 €"},"on_card":true},{"app_id":545519333,"name":"Amazon Prime Video","publisher_id":"297606954","publisher_name":"AMZN Mobile LLC","categories":[6016,6012],"subtitle":"Originals, films, séries","icon_url":"https://is2-ssl.mzstatic.com/image/thumb/Purple115/v4/ed/aa/e9/edaae999-304e-d5f0-c531-3cddbe8c7c0f/AppIcon-0-0-1x_U007emarketing-0-0-0-7-0-0-sRGB-0-0-0-GLES2_U002c0-512MB-85-220-0-0.png/1024x1024bb.png","offer":{"action_text":"OBTENIR","price":0,"price_formatted":"0,00 €"},"on_card":true},{"app_id":329913454,"name":"Crunchyroll","publisher_id":"329913457","publisher_name":"Ellation, Inc.","categories":[6016,6012],"subtitle":"Streaming d'anime et de films","icon_url":"https://is3-ssl.mzstatic.com/image/thumb/Purple125/v4/77/57/27/775727d7-2552-3f23-335f-f6a182b0fd39/AppIcon-0-0-1x_U007emarketing-0-0-0-10-0-0-sRGB-0-0-0-GLES2_U002c0-512MB-85-220-0-0.png/1024x1024bb.png","offer":{"action_text":"OBTENIR","price":0,"price_formatted":"0,00 €"},"on_card":true},{"app_id":1053134780,"name":"Molotov - TV en direct, replay","publisher_id":"1053134779","publisher_name":"Molotov","categories":[6016,6012],"subtitle":"TV en live, replay et VOD","icon_url":"https://is3-ssl.mzstatic.com/image/thumb/Purple125/v4/76/8e/34/768e345a-47cf-41a1-eed0-7f5ab3a52873/AppIcon-0-0-1x_U007emarketing-0-0-0-7-0-0-sRGB-0-0-0-GLES2_U002c0-512MB-85-220-0-0.png/1024x1024bb.png","offer":{"action_text":"OBTENIR","price":0,"price_formatted":"0,00 €"},"on_card":true},{"app_id":405028510,"name":"ARTE","publisher_id":"379981515","publisher_name":"ARTE.TV","categories":[6016,6006],"subtitle":"Replay, direct et exclusivités","icon_url":"https://is1-ssl.mzstatic.com/image/thumb/Purple115/v4/0c/8d/ea/0c8dea9b-67a8-c551-bab0-f64146be4028/AppIcon-1x_U007emarketing-0-7-0-0-85-220.png/1024x1024bb.png","offer":{"action_text":"OBTENIR","price":0,"price_formatted":"0,00 €"},"on_card":true},{"app_id":428835098,"name":"france.tv : direct et replay","publisher_id":"348684700","publisher_name":"France Télévisions","categories":[6016,6009],"subtitle":"Chaînes TV, séries & films ...","icon_url":"https://is1-ssl.mzstatic.com/image/thumb/Purple115/v4/60/66/94/6066946e-11ed-b2c1-db9b-af1245e3683c/AppIcon-0-0-1x_U007emarketing-0-0-0-7-0-0-sRGB-0-0-0-GLES2_U002c0-512MB-85-220-0-0.png/1024x1024bb.png","offer":{"action_text":"OBTENIR","price":0,"price_formatted":"0,00 €"},"on_card":true},{"app_id":1095795448,"name":"Kidjo Vidéos et Dessins Animés","publisher_id":"1095795447","publisher_name":"Kidjo","categories":[6016,6017],"subtitle":"Comptines pour les enfants","icon_url":"https://is4-ssl.mzstatic.com/image/thumb/Purple115/v4/54/25/21/542521c8-4143-d35a-df30-564bf5b5a037/AppIcon_summer-0-0-1x_U007emarketing-0-0-0-10-0-0-sRGB-0-0-0-GLES2_U002c0-512MB-85-220-0-0.png/1024x1024bb.png","offer":{"action_text":"OBTENIR","price":0,"price_formatted":"0,00 €"},"on_card":true},{"app_id":963076130,"name":"TFOU MAX • Dessins Animés","publisher_id":"306486391","publisher_name":"e-TF1","categories":[6016,6017],"subtitle":"Dessins animés, films, vidéos","icon_url":"https://is5-ssl.mzstatic.com/image/thumb/Purple114/v4/9b/42/f9/9b42f984-e259-dcad-d033-3fd15eae1c14/AppIcon-0-0-1x_U007emarketing-0-0-0-7-0-0-sRGB-0-0-0-GLES2_U002c0-512MB-85-220-0-0.png/1024x1024bb.png","offer":{"action_text":"OBTENIR","price":0,"price_formatted":"0,00 €"},"on_card":true},{"app_id":1466616493,"name":"STARZPLAY","publisher_id":"550221102","publisher_name":"Starz Entertainment, LLC","categories":[6016],"subtitle":null,"icon_url":"https://is1-ssl.mzstatic.com/image/thumb/Purple125/v4/f2/78/ee/f278ee12-db9b-acdf-887d-5c78c57b17df/AppIcon-1x_U007emarketing-0-10-0-85-220.png/1024x1024bb.png","offer":{"action_text":"OBTENIR","price":0,"price_formatted":"0,00 €"},"on_card":true},{"app_id":484672289,"name":"NBA Officiel : basket en live","publisher_id":"1536087365","publisher_name":"NBA MEDIA VENTURES, LLC","categories":[6004,6016],"subtitle":"Calendrier, replay et stats","icon_url":"https://is1-ssl.mzstatic.com/image/thumb/Purple125/v4/d1/19/0d/d1190d1c-dfa9-37da-3063-b975466f437f/AppIcon-0-0-1x_U007emarketing-0-0-0-7-0-0-sRGB-0-0-0-GLES2_U002c0-512MB-85-220-0-0.png/1024x1024bb.png","offer":{"action_text":"OBTENIR","price":0,"price_formatted":"0,00 €"},"on_card":true},{"app_id":1499688068,"name":"SALTO","publisher_id":"1499688067","publisher_name":"Salto France","categories":[6016],"subtitle":"TV et Streaming en illimité","icon_url":"https://is5-ssl.mzstatic.com/image/thumb/Purple115/v4/f0/e6/20/f0e6203d-dd2a-d3ea-9788-fe5360737b3c/AppIcon-0-0-1x_U007emarketing-0-0-0-7-0-0-sRGB-0-0-0-GLES2_U002c0-512MB-85-220-0-0.png/1024x1024bb.png","offer":{"action_text":"OBTENIR","price":0,"price_formatted":"0,00 €"},"on_card":true}],"substyle":"list"},{"position":5,"id":"1579326041","url":"https://apps.apple.com/fr/story/id1579326041","title":"Marvel Future Revolution","label":"LE JEU\nDU\nJOUR","short_description":"Soyez le héros du multivers.","style":"branded","artwork":{"url":"https://is3-ssl.mzstatic.com/image/thumb/Features125/v4/94/34/a9/9434a921-9bba-f19a-4c58-e9f012a7c6b7/source/3524x2160bb.png","text_colors":["8ecfd2","6aa3c8","74a8ad","5887a5"],"bg_color":"1c262e","alpha":false},"video_preview_url":null,"apps":[{"app_id":1453366542,"name":"MARVEL Future Revolution","publisher_id":"930364579","publisher_name":"Netmarble Corporation","categories":[6014,7014],"subtitle":"A new future begins!","icon_url":"https://is4-ssl.mzstatic.com/image/thumb/Purple115/v4/d2/85/5a/d2855ab7-67d0-7d99-d23a-a12b58515d94/AppIcon-0-0-1x_U007emarketing-0-0-0-7-0-0-sRGB-0-0-0-GLES2_U002c0-512MB-85-220-0-0.png/1024x1024bb.png","offer":{"action_text":"OBTENIR","price":0,"price_formatted":"0,00 €"},"on_card":true}],"substyle":"game_of_day"},{"position":6,"id":"1568602839","url":"https://apps.apple.com/fr/story/id1568602839","title":"Scribble Together","label":"L’APP\nDU\nJOUR","short_description":null,"style":"branded","artwork":{"url":"https://is1-ssl.mzstatic.com/image/thumb/Features125/v4/b1/b2/b7/b1b2b78f-cb36-6d4f-cd05-e80bf7252952/source/3524x2160bb.png","text_colors":["e1ae25","1ac4e5","bf8532","1b95cc"],"bg_color":"480072","alpha":false},"video_preview_url":null,"apps":[{"app_id":1266088066,"name":"Scribble Together Whiteboard","publisher_id":"1266088065","publisher_name":"Scribble Together","categories":[6007,6002],"subtitle":null,"icon_url":"https://is5-ssl.mzstatic.com/image/thumb/Purple125/v4/d8/c4/fe/d8c4fe57-cbe2-05a5-3359-6dcd844c95e1/AppIcon-0-1x_U007emarketing-0-7-0-0-sRGB-85-220.png/1024x1024bb.png","offer":{"action_text":"OBTENIR","price":0,"price_formatted":"0,00 €"},"on_card":true}],"substyle":"app_of_day"}]}