{"country":"FR","date":"2022-08-05T00:00:00Z","stories":[{"position":1,"id":"1629653623","url":"https://apps.apple.com/fr/story/id1629653623","title":"Découvrez Zoom One Pro","label":"ASTUCES DE PRO","short_description":null,"style":"content","artwork":{"url":"https://is1-ssl.mzstatic.com/image/thumb/Features112/v4/86/0c/29/860c297b-c082-c29c-cdc5-b6b79cd800b0/source/3524x2160bb.png","text_colors":["ebeae5","bec8c1","b3bbd8","91a1bc"],"bg_color":"0416a8","alpha":false},"video_preview_url":null,"apps":[{"app_id":546505307,"name":"ZOOM Cloud Meetings","publisher_id":"530594111","publisher_name":"Zoom Video Communications, Inc.","categories":[6000,6007],"subtitle":null,"icon_url":"https://is3-ssl.mzstatic.com/image/thumb/Purple112/v4/3b/bc/20/3bbc204d-1e99-5f63-31bc-ebc9133dc0e3/AppIcon-0-1x_U007emarketing-0-9-0-85-220.png/1024x1024bb.png","offer":{"action_text":"OBTENIR","price":0,"price_formatted":"0,00 €"},"on_card":true}],"substyle":"editorial"},{"position":2,"id":"1532049855","url":"https://apps.apple.com/fr/story/id1532049855","title":"Le top des apps de la semaine","label":"NOS FAVORIS","short_description":null,"style":"content","artwork":null,"video_preview_url":null,"apps":[{"app_id":997362197,"name":"InShot - Montage video & photo","publisher_id":"1619465920","publisher_name":"SHANTANU PTE. LTD.","categories":[6008,6016],"subtitle":"Éditeur de vidéo en musique","icon_url":"https://is5-ssl.mzstatic.com/image/thumb/Purple122/v4/f7/78/d8/f778d829-4857-f636-06e9-37761f0d8c3e/AppIcon-0-0-1x_U007emarketing-0-0-0-7-0-0-sRGB-0-0-0-GLES2_U002c0-512MB-85-220-0-0.png/1024x1024bb.png","offer":{"action_text":"OBTENIR","price":0,"price_formatted":"0,00 €"},"on_card":true},{"app_id":447188370,"name":"Snapchat","publisher_id":"446889612","publisher_name":"Snap, Inc.","categories":[6008,6005],"subtitle":"Partagez l'instant présent","icon_url":"https://is1-ssl.mzstatic.com/image/thumb/Purple112/v4/5e/ef/1c/5eef1c81-0af5-b4e5-9b0e-3d97e3f2edb6/AppIcon-0-0-1x_U007emarketing-0-0-0-5-0-0-sRGB-0-0-0-GLES2_U002c0-512MB-85-220-0-0.png/1024x1024bb.png","offer":{"action_text":"OBTENIR","price":0,"price_formatted":"0,00 €"},"on_card":true},{"app_id":547702041,"name":"Tinder - App de rencontre","publisher_id":"725634363","publisher_name":"Tinder Inc.","categories":[6012,6005],"subtitle":"Faites des rencontres","icon_url":"https://is3-ssl.mzstatic.com/image/thumb/Purple112/v4/e1/dd/43/e1dd4382-83ca-cd91-634e-dbabecc6a37d/AppIcon-1x_U007emarketing-0-7-0-85-220.png/1024x1024bb.png","offer":{"action_text":"OBTENIR","price":0,"price_formatted":"0,00 €"},"on_card":true},{"app_id":587366035,"name":"Picsart Montage Photo & Vidéo","publisher_id":"587366038","publisher_name":"PicsArt, Inc.","categories":[6008,6005],"subtitle":"Filtre/Retouche/Collage/Effet","icon_url":"https://is2-ssl.mzstatic.com/image/thumb/Purple122/v4/d9/3e/9e/d93e9e10-b6ed-2f52-6abe-081d6235d81c/AppIcon-0-0-1x_U007emarketing-0-0-0-7-0-0-sRGB-0-0-0-GLES2_U002c0-512MB-85-220-0-0.png/1024x1024bb.png","offer":{"action_text":"OBTENIR","price":0,"price_formatted":"0,00 €"},"on_card":true},{"app_id":351331194,"name":"Badoo - Rencontre en ligne","publisher_id":"351331197","publisher_name":"Badoo Software Ltd","categories":[6012,6005],"subtitle":"Tchat pour célibataires & amis","icon_url":"https://is5-ssl.mzstatic.com/image/thumb/Purple112/v4/94/53/d8/9453d836-a707-aa32-5a3f-4d97ce3e0138/AppIcon-1x_U007emarketing-0-7-0-85-220.png/1024x1024bb.png","offer":{"action_text":"OBTENIR","price":0,"price_formatted":"0,00 €"},"on_card":true},{"app_id":570060128,"name":"Duolingo","publisher_id":"570060151","publisher_name":"Duolingo","categories":[6017,6005],"subtitle":"Apprends l'anglais et plus","icon_url":"https://is3-ssl.mzstatic.com/image/thumb/Purple122/v4/27/8a/82/278a826a-5707-3695-211f-e1877b847374/AppIcon-0-1x_U007emarketing-0-7-0-85-220.png/1024x1024bb.png","offer":{"action_text":"OBTENIR","price":0,"price_formatted":"0,00 €"},"on_card":true},{"app_id":1446075923,"name":"Disney+","publisher_id":"284888248","publisher_name":"Disney","categories":[6016],"subtitle":"Un divertissement en continu","icon_url":"https://is4-ssl.mzstatic.com/image/thumb/Purple112/v4/21/e7/4c/21e74cfc-2ac2-9d11-9cf4-5cd4469c0c26/AppIcon-1x_U007emarketing-0-7-0-0-85-220.png/1024x1024bb.png","offer":{"action_text":"OBTENIR","price":0,"price_formatted":"0,00 €"},"on_card":true},{"app_id":544007664,"name":"YouTube","publisher_id":"281956209","publisher_name":"Google LLC","categories":[6008,6016],"subtitle":"Musique & Vidéos à regarder","icon_url":"https://is2-ssl.mzstatic.com/image/thumb/Purple122/v4/a7/b4/73/a7b473e0-d6d4-8138-627f-3290694f47c1/logo_youtube_color-0-0-1x_U007emarketing-0-0-0-6-0-0-sRGB-0-0-0-GLES2_U002c0-512MB-85-220-0-0.png/1024x1024bb.png","offer":{"action_text":"OBTENIR","price":0,"price_formatted":"0,00 €"},"on_card":true},{"app_id":897446215,"name":"Canva : Éditeur Photo et vidéo","publisher_id":"897446218","publisher_name":"Canva","categories":[6008,6007],"subtitle":"Graphisme/Design/Montage/Carte","icon_url":"https://is3-ssl.mzstatic.com/image/thumb/Purple122/v4/9a/ac/3b/9aac3b64-10d4-b507-b8f5-e4464482008f/AppIcon-0-0-1x_U007emarketing-0-0-0-7-0-0-sRGB-0-0-0-GLES2_U002c0-512MB-85-220-0-0.png/1024x1024bb.png","offer":{"action_text":"OBTENIR","price":0,"price_formatted":"0,00 €"},"on_card":true},{"app_id":545519333,"name":"Amazon Prime Video","publisher_id":"297606954","publisher_name":"AMZN Mobile LLC","categories":[6016,6012],"subtitle":"Originals, films, séries","icon_url":"https://is3-ssl.mzstatic.com/image/thumb/Purple112/v4/56/f8/f9/56f8f9f4-3d59-eb06-aebb-9598c7fc38a0/AppIcon-1x_U007emarketing-0-7-0-0-85-220-0.png/1024x1024bb.png","offer":{"action_text":"OBTENIR","price":0,"price_formatted":"0,00 €"},"on_card":true},{"app_id":445338486,"name":"LOVOO - App de rencontre","publisher_id":"445338489","publisher_name":"LOVOO GmbH apps","categories":[6012,6016],"subtitle":"Tchatche Gratuit & Rencontres","icon_url":"https://is3-ssl.mzstatic.com/image/thumb/Purple122/v4/d8/3f/08/d83f0854-0eae-142d-831b-2f297c3100ea/AppIcon-0-1x_U007emarketing-0-7-0-sRGB-85-220.png/1024x1024bb.png","offer":{"action_text":"OBTENIR","price":0,"price_formatted":"0,00 €"},"on_card":true},{"app_id":288429040,"name":"LinkedIn: Chercher des emplois","publisher_id":"288429043","publisher_name":"LinkedIn Corporation","categories":[6000],"subtitle":"Réseau d’affaires et emplois","icon_url":"https://is5-ssl.mzstatic.com/image/thumb/Purple112/v4/c8/5c/95/c85c9514-4934-c057-26c5-b21c6376b0b2/AppIcon-0-1x_U007emarketing-0-7-0-85-220.png/1024x1024bb.png","offer":{"action_text":"OBTENIR","price":0,"price_formatted":"0,00 €"},"on_card":true},{"app_id":835599320,"name":"TikTok : Ça commence avec toi","publisher_id":"1322881000","publisher_name":"TikTok Ltd.","categories":[6016,6008],"subtitle":"Vidéos, Musiques et LIVES","icon_url":"https://is3-ssl.mzstatic.com/image/thumb/Purple122/v4/e8/13/f5/e813f560-243c-abf2-6dae-a908f2217b8f/AppIcon_TikTok-0-0-1x_U007emarketing-0-0-0-7-0-0-sRGB-0-0-0-GLES2_U002c0-512MB-85-220-0-0.png/1024x1024bb.png","offer":{"action_text":"OBTENIR","price":0,"price_formatted":"0,00 €"},"on_card":true},{"app_id":985746746,"name":"Discord - Discute & Parle","publisher_id":"658886503","publisher_name":"Discord, Inc.","categories":[6005,6014],"subtitle":"Amis, communautés et gaming","icon_url":"https://is1-ssl.mzstatic.com/image/thumb/Purple122/v4/82/94/0e/82940ea1-f8b6-0579-6916-fd2fa6b00d97/AppIcon-0-0-1x_U007emarketing-0-0-0-7-0-0-sRGB-0-0-0-GLES2_U002c0-512MB-85-220-0-0.png/1024x1024bb.png","offer":{"action_text":"OBTENIR","price":0,"price_formatted":"0,00 €"},"on_card":true},{"app_id":333903271,"name":"Twitter","publisher_id":"296415947","publisher_name":"Twitter, Inc.","categories":[6009,6005],"subtitle":"Actualités et médias sociaux","icon_url":"https://is1-ssl.mzstatic.com/image/thumb/Purple122/v4/49/5d/9f/495d9fe2-40d4-2f06-5af9-a332292571be/ProductionAppIcon-1x_U007emarketing-0-7-0-0-0-85-220.png/1024x1024bb.png","offer":{"action_text":"OBTENIR","price":0,"price_formatted":"0,00 €"},"on_card":true},{"app_id":306310789,"name":"Wattpad","publisher_id":"306310792","publisher_name":"Wattpad Corp","categories":[6018,6016],"subtitle":null,"icon_url":"https://is5-ssl.mzstatic.com/image/thumb/Purple122/v4/ee/45/47/ee45477b-6ea7-3e4e-9774-ef4ce9ce02a8/AppIcon-0-1x_U007emarketing-0-7-0-85-220.png/1024x1024bb.png","offer":{"action_text":"OBTENIR","price":0,"price_formatted":"0,00 €"},"on_card":true},{"app_id":469337564,"name":"Adobe Acrobat Reader: Lire PDF","publisher_id":"331646274","publisher_name":"Adobe Inc.","categories":[6000,6007],"subtitle":"Convertisseur et lecteur PDF","icon_url":"https://is1-ssl.mzstatic.com/image/thumb/Purple112/v4/3f/ab/a0/3faba0e5-8d72-5cb9-614e-b9a8214bedae/AppIcon-0-1x_U007emarketing-0-7-0-85-220.png/1024x1024bb.png","offer":{"action_text":"OBTENIR","price":0,"price_formatted":"0,00 €"},"on_card":true}],"substyle":"list"},{"position":3,"id":"1599762531","url":"https://apps.apple.com/fr/story/id1599762531","title":"Top 10 des apps de bien-être","label":"LES INDISPENSABLES","short_description":null,"style":"media","artwork":{"url":"https://is4-ssl.mzstatic.com/image/thumb/Features126/v4/64/00/41/64004102-afd8-20dd-783c-8910cf2eeaeb/source/3524x2160bb.png","text_colors":["0e0d0c","181614","27231e","312c25"],"bg_color":"b49b7d","alpha":false},"video_preview_url":null,"apps":[{"app_id":314498713,"name":"BetterSleep: Dormez-mieux","publisher_id":"314498716","publisher_name":"Ipnos Software Inc.","categories":[6013],"subtitle":"Son, Musique et Méditation Zen","icon_url":"https://is1-ssl.mzstatic.com/image/thumb/Purple122/v4/80/09/78/80097856-254f-bad6-36c9-72744356301a/AppIcon-1x_U007emarketing-0-7-0-85-220.png/1024x1024bb.png","offer":{"action_text":"OBTENIR","price":0,"price_formatted":"0,00 €"},"on_card":true},{"app_id":1439590239,"name":"Alan Mind: thérapie bien-être","publisher_id":"1277025963","publisher_name":"Alan Health","categories":[6013,6012],"subtitle":"Stress, Motivation, Confiance","icon_url":"https://is1-ssl.mzstatic.com/image/thumb/Purple112/v4/69/83/c9/6983c906-9cae-a4d9-5294-76fdbd6cc9e8/AppIcon-Prod-0-0-1x_U007emarketing-0-0-0-10-0-0-sRGB-0-0-0-GLES2_U002c0-512MB-85-220-0-0.png/1024x1024bb.png","offer":{"action_text":"OBTENIR","price":0,"price_formatted":"0,00 €"},"on_card":true},{"app_id":1470585608,"name":"TaoZen Sons Détente & Sommeil","publisher_id":"452269707","publisher_name":"MWM","categories":[6013,6011],"subtitle":"Méditation Calme & Bruit Blanc","icon_url":"https://is5-ssl.mzstatic.com/image/thumb/Purple126/v4/e5/6c/0f/e56c0f44-b858-6665-40b2-98291dc10b35/AppIcon-1x_U007emarketing-0-7-0-85-220.png/1024x1024bb.png","offer":{"action_text":"OBTENIR","price":0,"price_formatted":"0,00 €"},"on_card":true},{"app_id":1073602315,"name":"Mind - Méditations guidées","publisher_id":"1438493510","publisher_name":"MIND AND CIE","categories":[6013,6012],"subtitle":"Méditation pleine conscience","icon_url":"https://is5-ssl.mzstatic.com/image/thumb/Purple116/v4/03/e8/39/03e83999-a495-e832-1964-ab08afc2cd46/AppIcon-0-0-1x_U007emarketing-0-0-0-7-0-0-sRGB-0-0-0-GLES2_U002c0-512MB-85-220-0-0.png/1024x1024bb.png","offer":{"action_text":"OBTENIR","price":0,"price_formatted":"0,00 €"},"on_card":true},{"app_id":1190294015,"name":"Meditopia:Méditation,Sommeil","publisher_id":"1144930469","publisher_name":"YEDI70 YAZILIM VE BILGI TEKNOLOJILERI ANONIM SIRKETI","categories":[6013,6012],"subtitle":"Relaxation,Sommeil,Motivation","icon_url":"https://is3-ssl.mzstatic.com/image/thumb/Purple112/v4/a1/d9/8e/a1d98ef6-a101-f222-2551-26630fdd50bc/AppIcon-0-1x_U007emarketing-0-7-0-0-0-85-220-0.png/1024x1024bb.png","offer":{"action_text":"OBTENIR","price":0,"price_formatted":"0,00 €"},"on_card":false},{"app_id":493145008,"name":"Headspace Méditation & Sommeil","publisher_id":"384434796","publisher_name":"Headspace Inc.","categories":[6013,6007],"subtitle":"Relaxation, bien-être, santé","icon_url":"https://is3-ssl.mzstatic.com/image/thumb/Purple122/v4/67/8a/d8/678ad8cb-b5a7-9788-4611-05502c677739/AppIcon-0-1x_U007emarketing-0-7-0-sRGB-85-220.png/1024x1024bb.png","offer":{"action_text":"OBTENIR","price":0,"price_formatted":"0,00 €"},"on_card":false},{"app_id":1346247457,"name":"Endel: écoute sons de sommeil","publisher_id":"1346247456","publisher_name":"Endel","categories":[6013,6012],"subtitle":"Relaxante pour mieux dormir","icon_url":"https://is3-ssl.mzstatic.com/image/thumb/Purple112/v4/75/72/30/757230f0-b85f-75e4-1f90-13ac83e9ffd9/AppIcon-1x_U007emarketing-0-10-0-85-220.png/1024x1024bb.png","offer":{"action_text":"OBTENIR","price":0,"price_formatted":"0,00 €"},"on_card":false},{"app_id":571800810,"name":"Calm: Sommeil & Méditation","publisher_id":"571800813","publisher_name":"Calm.com","categories":[6013,6012],"subtitle":"Sante, détente, sons, sleep","icon_url":"https://is1-ssl.mzstatic.com/image/thumb/Purple122/v4/51/12/21/511221d4-57a6-9aef-d80c-d03c5f066a73/AppIcon-0-1x_U007emarketing-0-10-0-85-220.png/1024x1024bb.png","offer":{"action_text":"OBTENIR","price":0,"price_formatted":"0,00 €"},"on_card":false},{"app_id":941222646,"name":"Petit BamBou : Méditation","publisher_id":"941222645","publisher_name":"FeelVeryBien","categories":[6013,6012],"subtitle":"Respiration & Relaxation","icon_url":"https://is5-ssl.mzstatic.com/image/thumb/Purple122/v4/50/af/0f/50af0f79-1a4c-d165-41a4-926fbd16b2ae/AppIcon-0-0-1x_U007emarketing-0-0-0-7-0-0-sRGB-0-0-0-GLES2_U002c0-512MB-85-220-0-0.png/1024x1024bb.png","offer":{"action_text":"OBTENIR","price":0,"price_formatted":"0,00 €"},"on_card":false},{"app_id":1203637303,"name":"Fabulous Routines & Habitudes","publisher_id":"1203637302","publisher_name":"Fabulous","categories":[6013,6012],"subtitle":"Motivation, Santé, Coaching","icon_url":"https://is2-ssl.mzstatic.com/image/thumb/Purple122/v4/5d/99/04/5d990411-ec0a-9570-6b2b-3c7eb74118e4/AppIcon-0-1x_U007emarketing-0-4-0-85-220.png/1024x1024bb.png","offer":{"action_text":"OBTENIR","price":0,"price_formatted":"0,00 €"},"on_card":false}],"substyle":null},{"position":4,"id":"1549897226","url":"https://apps.apple.com/fr/story/id1549897226","title":"Quelque chose de nouveau","label":"LA LISTE","short_description":null,"style":"content","artwork":null,"video_preview_url":null,"apps":[{"app_id":1547395841,"name":"Rise of Cultures","publisher_id":"435365770","publisher_name":"InnoGames","categories":[6014,7017,6016,7015],"subtitle":"Bâtis ta ville, vis l'Histoire","icon_url":"https://is1-ssl.mzstatic.com/image/thumb/Purple122/v4/95/1c/32/951c32d1-9fa4-246d-539d-16e832ec237d/AppIcon-1x_U007emarketing-0-7-0-85-220.png/1024x1024bb.png","offer":{"action_text":"OBTENIR","price":0,"price_formatted":"0,00 €"},"on_card":true},{"app_id":1314391359,"name":"FRAG Pro Shooter","publisher_id":"547556985","publisher_name":"Oh BiBi","categories":[6014,7003,7001],"subtitle":"Jeu de tir, 4 modes de jeux!","icon_url":"https://is2-ssl.mzstatic.com/image/thumb/Purple112/v4/07/18/e5/0718e59c-b28f-ea28-9631-a6b6cbbd0a16/AppIcon-0-0-1x_U007emarketing-0-0-0-7-0-0-sRGB-0-0-0-GLES2_U002c0-512MB-85-220-0-0.png/1024x1024bb.png","offer":{"action_text":"OBTENIR","price":0,"price_formatted":"0,00 €"},"on_card":true},{"app_id":1498198098,"name":"Angry Birds Journey","publisher_id":"298910979","publisher_name":"Rovio Entertainment Oyj","categories":[6014,7003,7012,6016],"subtitle":"Résolvez des casse-têtes !","icon_url":"https://is2-ssl.mzstatic.com/image/thumb/Purple122/v4/72/3d/ab/723dab7d-8162-0c28-acb2-335ade1991b5/AppIcon-1x_U007emarketing-0-7-0-85-220.png/1024x1024bb.png","offer":{"action_text":"OBTENIR","price":0,"price_formatted":"0,00 €"},"on_card":true},{"app_id":1480191929,"name":"Pocket Styler: Fashion Stars","publisher_id":"348389028","publisher_name":"Nordcurrent UAB","categories":[6014,6012,7015,7003],"subtitle":"Tout commence MAINTENANT !","icon_url":"https://is4-ssl.mzstatic.com/image/thumb/Purple122/v4/dd/d4/da/ddd4da81-1f12-9473-966e-ce3cd33b787f/AppIcon-0-0-1x_U007emarketing-0-0-0-7-0-0-sRGB-0-0-0-GLES2_U002c0-512MB-85-220-0-0.png/1024x1024bb.png","offer":{"action_text":"OBTENIR","price":0,"price_formatted":"0,00 €"},"on_card":true},{"app_id":1526098139,"name":"Happy Clinic","publisher_id":"348389028","publisher_name":"Nordcurrent UAB","categories":[6014,6016,7015,7003],"subtitle":"Gérez l'hôpital de vos rêves !","icon_url":"https://is2-ssl.mzstatic.com/image/thumb/Purple122/v4/ec/d3/bf/ecd3bf2c-4184-5664-4903-de64dd33c6fd/AppIcon-0-0-1x_U007emarketing-0-0-0-7-0-0-sRGB-0-0-0-GLES2_U002c0-512MB-85-220-0-0.png/1024x1024bb.png","offer":{"action_text":"OBTENIR","price":0,"price_formatted":"0,00 €"},"on_card":true},{"app_id":1509449529,"name":"Rivengard","publisher_id":"1057938692","publisher_name":"Snowprint Studios AB","categories":[6014,7017,7014],"subtitle":"RPG tactique d'heroic-fantasy","icon_url":"https://is1-ssl.mzstatic.com/image/thumb/Purple112/v4/80/77/72/8077720f-6960-2959-9357-2b9f39199b11/AppIcon-0-0-1x_U007emarketing-0-0-0-7-0-0-sRGB-0-0-0-GLES2_U002c0-512MB-85-220-0-0.png/1024x1024bb.png","offer":{"action_text":"OBTENIR","price":0,"price_formatted":"0,00 €"},"on_card":true},{"app_id":868013618,"name":"Best Fiends - Jeux de match 3","publisher_id":"868013621","publisher_name":"Seriously","categories":[6014,7012,7002],"subtitle":"Jeu d'action-réflexion amusant","icon_url":"https://is2-ssl.mzstatic.com/image/thumb/Purple112/v4/b7/25/9c/b7259c74-177b-4f9d-2e5d-bb0e7d75ac45/AppIcon-0-0-1x_U007emarketing-0-0-0-4-0-0-sRGB-0-0-0-GLES2_U002c0-512MB-85-220-0-0.png/1024x1024bb.png","offer":{"action_text":"OBTENIR","price":0,"price_formatted":"0,00 €"},"on_card":true},{"app_id":1471999779,"name":"Traffic Puzzle","publisher_id":"1222929957","publisher_name":"Huuuge Global Ltd.","categories":[6014,7003,7012],"subtitle":"Revolutionary Match 3 Game!","icon_url":"https://is1-ssl.mzstatic.com/image/thumb/Purple122/v4/ba/b1/8d/bab18db5-b8fb-ab03-4aee-96683972dfb4/AppIcon-1x_U007emarketing-0-7-0-85-220.png/1024x1024bb.png","offer":{"action_text":"OBTENIR","price":0,"price_formatted":"0,00 €"},"on_card":true},{"app_id":1517765834,"name":"SpotRacers - Car Racing Game","publisher_id":"1510937279","publisher_name":"Level Up Garage ApS","categories":[6014,7001,7013],"subtitle":"Collectez, ajustez, roulez!","icon_url":"https://is1-ssl.mzstatic.com/image/thumb/Purple112/v4/65/16/a8/6516a8a3-24f5-77ce-285f-8bedcdc82b56/AppIcon-1x_U007emarketing-0-7-0-85-220.png/1024x1024bb.png","offer":{"action_text":"OBTENIR","price":0,"price_formatted":"0,00 €"},"on_card":true},{"app_id":1202788573,"name":"Albion Online","publisher_id":"645480626","publisher_name":"Sandbox Interactive GmbH","categories":[6014,7001,7014],"subtitle":"MMORPG Sandbox","icon_url":"https://is2-ssl.mzstatic.com/image/thumb/Purple122/v4/26/85/24/26852458-4a8e-a214-036a-9edd0a78b5a4/AppIcon-1x_U007emarketing-0-7-0-85-220.png/1024x1024bb.png","offer":{"action_text":"OBTENIR","price":0,"price_formatted":"0,00 €"},"on_card":true},{"app_id":1222489978,"name":"Airplane Chefs: Jeu de Cuisine","publisher_id":"348389028","publisher_name":"Nordcurrent UAB","categories":[6014,7001,6016,7003],"subtitle":"Le chef du ciel, c'est vous !","icon_url":"https://is2-ssl.mzstatic.com/image/thumb/Purple112/v4/92/38/9c/92389c1e-0dad-1fbb-5cc7-b726f8517d56/AppIcon-0-0-1x_U007emarketing-0-0-0-7-0-0-sRGB-0-0-0-GLES2_U002c0-512MB-85-220-0-0.png/1024x1024bb.png","offer":{"action_text":"OBTENIR","price":0,"price_formatted":"0,00 €"},"on_card":true},{"app_id":1537951774,"name":"GT Manager","publisher_id":"1438863511","publisher_name":"The Tiny Digital Factory","categories":[6014,7013,7015],"subtitle":"Racing Manager - Motorsport","icon_url":"https://is3-ssl.mzstatic.com/image/thumb/Purple112/v4/a0/be/bb/a0bebb75-8d34-2726-c6f6-052fb54c977d/AppIcon-1x_U007emarketing-0-7-0-85-220.png/1024x1024bb.png","offer":{"action_text":"OBTENIR","price":0,"price_formatted":"0,00 €"},"on_card":true},{"app_id":1476378632,"name":"Let's Create! Pottery 2","publisher_id":"306712040","publisher_name":"Infinite Dreams Inc.","categories":[6014,7009,6016,7003],"subtitle":null,"icon_url":"https://is1-ssl.mzstatic.com/image/thumb/Purple122/v4/77/1d/1a/771d1a17-6dce-ed00-9f91-39a737a4678f/AppIcon-1x_U007emarketing-0-7-0-85-220.png/1024x1024bb.png","offer":{"action_text":"OBTENIR","price":0,"price_formatted":"0,00 €"},"on_card":true},{"app_id":1475163222,"name":"Ultimate Golf!","publisher_id":"337457683","publisher_name":"Miniclip.com","categories":[6014,6004,7016,7015],"subtitle":"Jeux de simulateur de golf 3D","icon_url":"https://is1-ssl.mzstatic.com/image/thumb/Purple112/v4/0f/37/38/0f373884-11ff-fb16-df82-bd7033bbd52b/AppIcon-1x_U007emarketing-0-7-0-85-220.png/1024x1024bb.png","offer":{"action_text":"OBTENIR","price":0,"price_formatted":"0,00 €"},"on_card":true},{"app_id":859148736,"name":"EMERGENCY HQ - Jeux de Pompier","publisher_id":"321227098","publisher_name":"Promotion Software GmbH","categories":[6014,7015,6016,7017],"subtitle":"Sauvez des vies !","icon_url":"https://is1-ssl.mzstatic.com/image/thumb/Purple112/v4/0c/7d/9b/0c7d9b6f-b42e-c80a-0411-f329c5a5e8ea/AppIcon-1x_U007emarketing-0-7-0-85-220.png/1024x1024bb.png","offer":{"action_text":"OBTENIR","price":0,"price_formatted":"0,00 €"},"on_card":true},{"app_id":1492928510,"name":"1sland","publisher_id":"1157484553","publisher_name":"nada studio, sl","categories":[6014,7017,7002],"subtitle":"Paddle Royale","icon_url":"https://is2-ssl.mzstatic.com/image/thumb/Purple112/v4/1c/f3/e7/1cf3e76c-3221-cd8d-4959-09c9df3ebbdb/AppIcon-1x_U007emarketing-0-7-0-85-220.png/1024x1024bb.png","offer":{"action_text":"OBTENIR","price":0,"price_formatted":"0,00 €"},"on_card":true},{"app_id":1539133066,"name":"There Is No Game: WD","publisher_id":"1539030917","publisher_name":"Draw Me A Pixel","categories":[6014,7012,7002],"subtitle":"Wrong Dimension","icon_url":"https://is5-ssl.mzstatic.com/image/thumb/Purple116/v4/27/6d/53/276d5334-c777-5399-d5c1-752fd0cbfa63/AppIcon-0-0-1x_U007emarketing-0-0-0-7-0-0-sRGB-0-0-0-GLES2_U002c0-512MB-85-220-0-0.png/1024x1024bb.png","offer":{"action_text":"Acheter","price":499,"price_formatted":"4,99 €"},"on_card":true},{"app_id":833517462,"name":"Just Dance Now","publisher_id":"317644720","publisher_name":"Ubisoft","categories":[6014,7011,7003],"subtitle":null,"icon_url":"https://is4-ssl.mzstatic.com/image/thumb/Purple112/v4/a4/cb/52/a4cb5298-d03a-30ff-18fc-00a2d97a0b89/AppIcon-0-0-1x_U007emarketing-0-0-0-7-0-0-sRGB-0-0-0-GLES2_U002c0-512MB-85-220-0-0.png/1024x1024bb.png","offer":{"action_text":"OBTENIR","price":0,"price_formatted":"0,00 €"},"on_card":true},{"app_id":1492002834,"name":"Railways!","publisher_id":"1088875165","publisher_name":"INFINITY GAMES, LDA","categories":[6014,7012,7015],"subtitle":"Contrôlez la circulation!","icon_url":"https://is1-ssl.mzstatic.com/image/thumb/Purple122/v4/26/ad/b8/26adb88a-e6c2-d742-dc4c-b67f68e1cb6e/AppIcon-0-0-1x_U007emarketing-0-0-0-7-0-0-sRGB-0-0-0-GLES2_U002c0-512MB-85-220-0-0.png/1024x1024bb.png","offer":{"action_text":"Acheter","price":199,"price_formatted":"1,99 €"},"on_card":true},{"app_id":1523633394,"name":"SpongeBob SquarePants","publisher_id":"316574911","publisher_name":"HandyGames","categories":[6014,7001,7002],"subtitle":"Battle for Bikini Bottom","icon_url":"https://is1-ssl.mzstatic.com/image/thumb/Purple116/v4/24/be/b2/24beb282-3c76-77fa-9b13-0b9788794b3e/AppIcon-0-0-1x_U007emarketing-0-0-0-7-0-0-sRGB-0-0-0-GLES2_U002c0-512MB-85-220-0-0.png/1024x1024bb.png","offer":{"action_text":"Acheter","price":999,"price_formatted":"9,99 €"},"on_card":true},{"app_id":1049876497,"name":"GeoGuessr","publisher_id":"975384517","publisher_name":"GeoGuessr AB","categories":[6014,6017,7018],"subtitle":null,"icon_url":"https://is4-ssl.mzstatic.com/image/thumb/Purple112/v4/ad/3d/da/ad3dda83-9559-d1d8-862f-ee54863caae9/AppIcon-0-1x_U007emarketing-0-7-0-85-220.png/1024x1024bb.png","offer":{"action_text":"OBTENIR","price":0,"price_formatted":"0,00 €"},"on_card":false},{"app_id":1230892664,"name":"Smashing Four: Jeu Smash Hit","publisher_id":"594449005","publisher_name":"Geewa","categories":[6014,7017],"subtitle":"PvP de stratégie multijoueur","icon_url":"https://is5-ssl.mzstatic.com/image/thumb/Purple112/v4/9c/d7/3a/9cd73a50-dbec-1321-15c5-2316308e163f/AppIcon-0-0-1x_U007emarketing-0-0-0-7-0-0-sRGB-0-0-0-GLES2_U002c0-512MB-85-220-0-0.png/1024x1024bb.png","offer":{"action_text":"OBTENIR","price":0,"price_formatted":"0,00 €"},"on_card":false},{"app_id":1546191619,"name":"F-Sim|Space Shuttle 2","publisher_id":"352670058","publisher_name":"SkyTale Software GmbH","categories":[6014,6017,7013,7015],"subtitle":null,"icon_url":"https://is4-ssl.mzstatic.com/image/thumb/Purple115/v4/ae/71/46/ae714648-2c88-738d-ea55-988e011a40dd/AppIcon-1x_U007emarketing-0-7-0-85-220.png/1024x1024bb.png","offer":{"action_text":"Acheter","price":499,"price_formatted":"4,99 €"},"on_card":false},{"app_id":1311511672,"name":"Transit King Tycoon: Seaport","publisher_id":"1179301408","publisher_name":"BON Games","categories":[6014,6016,7015,7017],"subtitle":"City builder & Business tycoon","icon_url":"https://is1-ssl.mzstatic.com/image/thumb/Purple112/v4/6d/d1/08/6dd1089e-d19e-0b55-23f3-3672bc089683/AppIcon-0-0-1x_U007emarketing-0-0-0-7-0-0-sRGB-0-0-0-GLES2_U002c0-512MB-85-220-0-0.png/1024x1024bb.png","offer":{"action_text":"OBTENIR","price":0,"price_formatted":"0,00 €"},"on_card":false},{"app_id":1507936643,"name":"Boom Slingers","publisher_id":"1507936642","publisher_name":"Boom Corp","categories":[6014,7001,7017],"subtitle":null,"icon_url":"https://is2-ssl.mzstatic.com/image/thumb/Purple122/v4/13/59/df/1359df97-7986-4b44-857c-13a08198cb82/AppIcon-0-0-1x_U007emarketing-0-0-0-7-0-0-sRGB-0-0-0-GLES2_U002c0-512MB-85-220-0-0.png/1024x1024bb.png","offer":{"action_text":"OBTENIR","price":0,"price_formatted":"0,00 €"},"on_card":false},{"app_id":1549914827,"name":"Railroad Ink Challenge","publisher_id":"1460296043","publisher_name":"Horrible Guild","categories":[6014,7004,7017],"subtitle":"Le jeu de dés et de routes","icon_url":"https://is3-ssl.mzstatic.com/image/thumb/Purple116/v4/8f/6f/ca/8f6fca16-9097-d348-b5b9-06cf4fdaef5b/AppIcon-0-0-1x_U007emarketing-0-0-0-7-0-0-sRGB-0-0-0-GLES2_U002c0-512MB-85-220-0-0.png/1024x1024bb.png","offer":{"action_text":"Acheter","price":399,"price_formatted":"3,99 €"},"on_card":false},{"app_id":653508448,"name":"Monster Legends","publisher_id":"403274694","publisher_name":"Socialpoint","categories":[6014,7017,7014],"subtitle":"Elève tes monstres et combats!","icon_url":"https://is5-ssl.mzstatic.com/image/thumb/Purple122/v4/15/1f/8e/151f8e51-a351-9908-4a17-829f44f79583/AppIcon-0-0-1x_U007emarketing-0-0-0-7-0-0-sRGB-0-0-0-GLES2_U002c0-512MB-85-220-0-0.png/1024x1024bb.png","offer":{"action_text":"OBTENIR","price":0,"price_formatted":"0,00 €"},"on_card":false},{"app_id":1413287364,"name":"Redecor - Home Design Makeover","publisher_id":"1413287363","publisher_name":"Reworks","categories":[6014,6012,7015],"subtitle":"Sharpen your decorating skills","icon_url":"https://is3-ssl.mzstatic.com/image/thumb/Purple112/v4/ee/a2/f1/eea2f183-c24f-41d3-9a0b-23c9c0e7c2cd/AppIcon-0-0-1x_U007emarketing-0-0-0-7-0-0-sRGB-0-0-0-GLES2_U002c0-512MB-85-220-0-0.png/1024x1024bb.png","offer":{"action_text":"OBTENIR","price":0,"price_formatted":"0,00 €"},"on_card":false},{"app_id":1520374873,"name":"Merge Friends","publisher_id":"1504885784","publisher_name":"Skunkworks","categories":[6014,7015,7012],"subtitle":"Reconstruis, répare, rénove","icon_url":"https://is1-ssl.mzstatic.com/image/thumb/Purple112/v4/f0/9e/ba/f09eba93-0491-4190-78b5-0710d925d4b0/AppIcon-1x_U007emarketing-0-7-0-85-220.png/1024x1024bb.png","offer":{"action_text":"OBTENIR","price":0,"price_formatted":"0,00 €"},"on_card":false},{"app_id":1566838404,"name":"Slash & Roll: Multijoueur RPG","publisher_id":"1079884679","publisher_name":"Gamesture Sp. z o.o.","categories":[6014,7014,7001],"subtitle":"Jeu a plusieurs en ligne","icon_url":"https://is2-ssl.mzstatic.com/image/thumb/Purple112/v4/cc/48/71/cc4871f9-2572-e9c9-1946-1a96943bae21/AppIcon-0-0-1x_U007emarketing-0-0-0-7-0-0-sRGB-0-0-0-GLES2_U002c0-512MB-85-220-0-0.png/1024x1024bb.png","offer":{"action_text":"OBTENIR","price":0,"price_formatted":"0,00 €"},"on_card":false},{"app_id":1573005612,"name":"Warhammer AoS: Soul Arena","publisher_id":"1435787633","publisher_name":"Trophy Games ApS","categories":[6014,7017,7004],"subtitle":"Be the auto chess champion","icon_url":"https://is2-ssl.mzstatic.com/image/thumb/Purple112/v4/6b/d6/89/6bd68967-3cf6-7649-9fac-4157ed4a5f86/AppIcon-0-0-1x_U007emarketing-0-0-0-7-0-0-sRGB-0-0-0-GLES2_U002c0-512MB-85-220-0-0.png/1024x1024bb.png","offer":{"action_text":"OBTENIR","price":0,"price_formatted":"0,00 €"},"on_card":false},{"app_id":1484442152,"name":"Merge Mansion","publisher_id":"974585521","publisher_name":"Metacore Games Oy","categories":[6014,7012],"subtitle":"Un manoir plein de mystères !","icon_url":"https://is4-ssl.mzstatic.com/image/thumb/Purple122/v4/d8/65/f2/d865f229-c2ac-b721-902f-99062cc87615/AppIcon-1x_U007emarketing-0-7-0-85-220.png/1024x1024bb.png","offer":{"action_text":"OBTENIR","price":0,"price_formatted":"0,00 €"},"on_card":false},{"app_id":1046846443,"name":"Hungry Shark World","publisher_id":"317644720","publisher_name":"Ubisoft","categories":[6014,7001,7003,6016],"subtitle":"Jeu officiel de la Shark Week!","icon_url":"https://is3-ssl.mzstatic.com/image/thumb/Purple122/v4/1a/12/3c/1a123c9a-dff4-0764-1a4f-375a456b6c1d/AppIcon-0-0-1x_U007emarketing-0-0-0-10-0-0-sRGB-0-0-0-GLES2_U002c0-512MB-85-220-0-0.png/1024x1024bb.png","offer":{"action_text":"OBTENIR","price":0,"price_formatted":"0,00 €"},"on_card":false},{"app_id":698255242,"name":"Geometry Dash Lite","publisher_id":"414027834","publisher_name":"RobTop Games AB","categories":[6014,7003,6016,7011],"subtitle":null,"icon_url":"https://is1-ssl.mzstatic.com/image/thumb/Purple112/v4/2a/6f/ea/2a6feaae-3202-5356-eb1b-409208bcb0af/AppIcon-0-0-1x_U007emarketing-0-0-0-10-0-0-sRGB-0-0-0-GLES2_U002c0-512MB-85-220-0-0.png/1024x1024bb.png","offer":{"action_text":"OBTENIR","price":0,"price_formatted":"0,00 €"},"on_card":false}],"substyle":"list"},{"position":5,"id":"1620398206","url":"https://apps.apple.com/fr/story/id1620398206","title":"Jurassic World: le jeu","label":"LE JEU\nDU\nJOUR","short_description":"Amusez-vous dans ce parc de dinosaures de rêve.","style":"branded","artwork":{"url":"https://is1-ssl.mzstatic.com/image/thumb/Features122/v4/fa/b3/c8/fab3c8ab-89c3-8af3-4280-ae467b336450/source/3524x2160bb.png","text_colors":["ffffff","ffffff","35342e","545449"],"bg_color":"d2d5bf","alpha":false},"video_preview_url":null,"apps":[{"app_id":791211390,"name":"Jurassic World™: le jeu","publisher_id":"293912963","publisher_name":"Ludia","categories":[6014,6016,7015,7002],"subtitle":"Le Parc est ouvert!","icon_url":"https://is1-ssl.mzstatic.com/image/thumb/Purple122/v4/53/11/d7/5311d7f5-5717-ee68-76df-f8423b04331f/AppIcon-0-0-1x_U007emarketing-0-0-0-7-0-0-sRGB-0-0-0-GLES2_U002c0-512MB-85-220-0-0.png/1024x1024bb.png","offer":{"action_text":"OBTENIR","price":0,"price_formatted":"0,00 €"},"on_card":true}],"substyle":"game_of_day"},{"position":6,"id":"1576320690","url":"https://apps.apple.com/fr/story/id1576320690","title":"GoodNotes 5","label":"L’APP\nDU\nJOUR","short_description":"Un carnet de notes numérique qui donne l’impression d’écrire sur papier.","style":"branded","artwork":{"url":"https://is3-ssl.mzstatic.com/image/thumb/Features125/v4/7e/b2/a2/7eb2a28e-3f85-f0b4-8925-e32135b6ce46/source/3524x2160bb.png","text_colors":["0d0a07","0d0b09","2f2c25","302d27"],"bg_color":"fcf7db","alpha":false},"video_preview_url":null,"apps":[{"app_id":1444383602,"name":"GoodNotes 5","publisher_id":"424587624","publisher_name":"Time Base Technology Limited","categories":[6007,6017],"subtitle":"Notes et annotation de PDF","icon_url":"https://is5-ssl.mzstatic.com/image/thumb/Purple122/v4/0a/1d/24/0a1d246f-e37e-6ebd-1e76-37eb9d7c8c26/AppIcon-0-1x_U007emarketing-0-0-0-7-0-0-sRGB-85-220.png/1024x1024bb.png","offer":{"action_text":"OBTENIR","price":0,"price_formatted":"0,00 €"},"on_card":true}],"substyle":"app_of_day"}]}