{"country":"CA","date":"2021-10-18T00:00:00Z","stories":[{"position":1,"id":"1564879721","url":"https://apps.apple.com/ca/story/id1564879721","title":"5 New Games We Love","label":"OUR FAVOURITES","short_description":"This week’s favourites.","style":"media","artwork":{"url":"https://is2-ssl.mzstatic.com/image/thumb/Features125/v4/36/9f/35/369f351a-a38c-ead0-3a9e-4405799d8148/source/3524x2160bb.png","text_colors":["e48c64","de5745","b37056","ae483d"],"bg_color":"141422","alpha":false},"video_preview_url":null,"apps":[{"app_id":1510325826,"name":"Switchcraft: Magical Match 3","publisher_id":"461402737","publisher_name":"wooga","categories":[6014,7012],"subtitle":"Choose how the mystery unfolds","icon_url":"https://is1-ssl.mzstatic.com/image/thumb/Purple115/v4/ec/50/75/ec507568-e705-7d5a-d7d4-e8ea9688b7c2/AppIcon-1x_U007emarketing-0-7-0-85-220.png/1024x1024bb.png","offer":{"action_text":"GET","price":0,"price_formatted":"$0.00"},"on_card":true},{"app_id":1543399979,"name":"Chess Clash - Play Online","publisher_id":"337457683","publisher_name":"Miniclip.com","categories":[6014,7004,7017,6016],"subtitle":"2 player puzzle board game","icon_url":"https://is1-ssl.mzstatic.com/image/thumb/Purple125/v4/06/e6/33/06e633a0-1d07-dbcd-0386-36d174b07998/AppIcon-1x_U007emarketing-0-7-0-0-85-220.png/1024x1024bb.png","offer":{"action_text":"GET","price":0,"price_formatted":"$0.00"},"on_card":true},{"app_id":1583933898,"name":"sugar (game)","publisher_id":"568141787","publisher_name":"Bart Bonte","categories":[6014,7012,7003],"subtitle":"Draw to get sugar in the cups","icon_url":"https://is4-ssl.mzstatic.com/image/thumb/Purple115/v4/14/14/68/14146891-5816-d847-2474-59e744b39d3f/AppIcon-1x_U007emarketing-0-0-GLES2_U002c0-512MB-sRGB-0-0-0-85-220-0-0-0-8.png/1024x1024bb.png","offer":{"action_text":"GET","price":0,"price_formatted":"$0.00"},"on_card":true},{"app_id":1541160673,"name":"Merge Inn - Tasty Match Puzzle","publisher_id":"1481075166","publisher_name":"Original Games OU","categories":[6014,7003,7012,6023],"subtitle":"Merge to cook tasty food!","icon_url":"https://is5-ssl.mzstatic.com/image/thumb/Purple125/v4/b8/4a/fd/b84afd07-e6dc-411c-e837-3f96e1322f00/AppIcon-0-0-1x_U007emarketing-0-0-0-7-0-0-sRGB-0-0-0-GLES2_U002c0-512MB-85-220-0-0.png/1024x1024bb.png","offer":{"action_text":"GET","price":0,"price_formatted":"$0.00"},"on_card":true},{"app_id":1541520872,"name":"PIPES: Zen Garden","publisher_id":"1088875165","publisher_name":"WebAvenue Unipessoal Lda","categories":[6014,6016,7012,7011],"subtitle":"Grow your relaxing Zen Garden","icon_url":"https://is3-ssl.mzstatic.com/image/thumb/Purple125/v4/38/24/df/3824df78-3f6f-a8da-9e39-2602caef0098/AppIcon-0-0-1x_U007emarketing-0-0-0-7-0-0-sRGB-0-0-0-GLES2_U002c0-512MB-85-220-0-0.png/1024x1024bb.png","offer":{"action_text":"GET","price":0,"price_formatted":"$0.00"},"on_card":false}],"substyle":null},{"position":2,"id":"1492287158","url":"https://apps.apple.com/ca/story/id1492287158","title":"What We’re Playing","label":"OUR FAVOURITES","short_description":"The best iPhone and iPad games on the App Store.","style":"content","artwork":null,"video_preview_url":null,"apps":[{"app_id":805603214,"name":"Asphalt 9: Legends","publisher_id":"282764297","publisher_name":"Gameloft","categories":[6014,7016,7013,6016],"subtitle":"Sport Car Racing Game","icon_url":"https://is4-ssl.mzstatic.com/image/thumb/Purple125/v4/dc/c8/44/dcc84402-48ee-5a6a-c5ec-f3e165312735/AppIcon-1x_U007emarketing-0-8-0-85-220.png/1024x1024bb.png","offer":{"action_text":"GET","price":0,"price_formatted":"$0.00"},"on_card":true},{"app_id":572395608,"name":"Temple Run 2","publisher_id":"284899742","publisher_name":"Imangi Studios, LLC","categories":[6014,7002,6016,7001],"subtitle":"Grab the Idol and run!","icon_url":"https://is3-ssl.mzstatic.com/image/thumb/Purple115/v4/13/a3/b5/13a3b58b-b96e-f5bf-520b-0e392ac3506a/AppIcon-0-0-1x_U007emarketing-0-0-0-9-0-0-sRGB-0-0-0-GLES2_U002c0-512MB-85-220-0-0.png/1024x1024bb.png","offer":{"action_text":"GET","price":0,"price_formatted":"$0.00"},"on_card":true},{"app_id":1485854536,"name":"The Lord of the Rings: War","publisher_id":"1485225410","publisher_name":"NETEASE INTERACTIVE ENTERTAINMENT PTE. LTD","categories":[6014,7015,7017],"subtitle":"One Ring to Rule Them All","icon_url":"https://is5-ssl.mzstatic.com/image/thumb/Purple115/v4/5d/8c/58/5d8c5860-8ac1-2cec-e872-7778d4b3d827/AppIcon-0-0-1x_U007emarketing-0-0-0-10-0-0-sRGB-0-0-0-GLES2_U002c0-512MB-85-220-0-0.png/1024x1024bb.png","offer":{"action_text":"GET","price":0,"price_formatted":"$0.00"},"on_card":true},{"app_id":1541160673,"name":"Merge Inn - Tasty Match Puzzle","publisher_id":"1481075166","publisher_name":"Original Games OU","categories":[6014,7003,7012,6023],"subtitle":"Merge to cook tasty food!","icon_url":"https://is5-ssl.mzstatic.com/image/thumb/Purple125/v4/b8/4a/fd/b84afd07-e6dc-411c-e837-3f96e1322f00/AppIcon-0-0-1x_U007emarketing-0-0-0-7-0-0-sRGB-0-0-0-GLES2_U002c0-512MB-85-220-0-0.png/1024x1024bb.png","offer":{"action_text":"GET","price":0,"price_formatted":"$0.00"},"on_card":true},{"app_id":459035295,"name":"Top Eleven Be a Soccer Manager","publisher_id":"664666426","publisher_name":"Nordeus","categories":[6014,6004,7016,7015],"subtitle":"Soccer Management Game 2022","icon_url":"https://is3-ssl.mzstatic.com/image/thumb/Purple115/v4/37/6c/ea/376ceaa3-853f-2404-c4f1-e7eaf31136fb/AppIcon-1x_U007emarketing-0-7-0-0-85-220.png/1024x1024bb.png","offer":{"action_text":"GET","price":0,"price_formatted":"$0.00"},"on_card":true},{"app_id":1465097065,"name":"Infinite Galaxy","publisher_id":"1300436103","publisher_name":"CAMEL GAMES LIMITED","categories":[6014,7017,7015],"subtitle":"Command your space fleet","icon_url":"https://is4-ssl.mzstatic.com/image/thumb/Purple125/v4/a4/e4/67/a4e46768-3c0a-353d-e07d-c4c970665945/AppIcon-0-0-1x_U007emarketing-0-0-0-7-0-0-sRGB-0-0-0-GLES2_U002c0-512MB-85-220-0-0.png/1024x1024bb.png","offer":{"action_text":"GET","price":0,"price_formatted":"$0.00"},"on_card":true},{"app_id":1521483641,"name":"Beatstar","publisher_id":"1454690169","publisher_name":"Space Ape Ltd","categories":[6014,7011,7003,6011],"subtitle":"Touch Your Music","icon_url":"https://is1-ssl.mzstatic.com/image/thumb/Purple125/v4/b1/55/3f/b1553f92-343a-b90b-7652-d96e8744f1ac/AppIcon-1x_U007emarketing-0-7-0-85-220.png/1024x1024bb.png","offer":{"action_text":"GET","price":0,"price_formatted":"$0.00"},"on_card":true},{"app_id":1456213261,"name":"Mobile Legends: Adventure","publisher_id":"910435102","publisher_name":"Shanghai Moonton Technology Co., Ltd.","categories":[6014,7017,7014],"subtitle":"Adventure RPG: Idle & Gacha","icon_url":"https://is1-ssl.mzstatic.com/image/thumb/Purple115/v4/55/c9/17/55c917c3-ec9b-0879-bd38-7d37042d6d5d/AppIcon-0-0-1x_U007emarketing-0-0-0-9-0-0-sRGB-0-0-0-GLES2_U002c0-512MB-85-220-0-0.png/1024x1024bb.png","offer":{"action_text":"GET","price":0,"price_formatted":"$0.00"},"on_card":true},{"app_id":1314391359,"name":"FRAG Pro Shooter","publisher_id":"547556985","publisher_name":"Oh BiBi","categories":[6014,7003,7001],"subtitle":"PvP Gun Battle: Shooting Game","icon_url":"https://is5-ssl.mzstatic.com/image/thumb/Purple125/v4/25/48/e8/2548e8e9-2900-c64f-99fc-13e4182c8c10/AppIcon-0-0-1x_U007emarketing-0-0-0-7-0-0-sRGB-0-0-0-GLES2_U002c0-512MB-85-220-0-0.png/1024x1024bb.png","offer":{"action_text":"GET","price":0,"price_formatted":"$0.00"},"on_card":true},{"app_id":1482155847,"name":"Royal Match","publisher_id":"1482155846","publisher_name":"Dream Games, Ltd.","categories":[6014,7003,7012],"subtitle":"Swipe colors & solve puzzles","icon_url":"https://is2-ssl.mzstatic.com/image/thumb/Purple115/v4/d9/d2/a4/d9d2a433-dcca-70aa-65e3-2521c9ff1d06/AppIcon-0-0-1x_U007emarketing-0-0-0-7-0-0-sRGB-0-0-0-GLES2_U002c0-512MB-85-220-0-0.png/1024x1024bb.png","offer":{"action_text":"GET","price":0,"price_formatted":"$0.00"},"on_card":true},{"app_id":880047117,"name":"Angry Birds 2","publisher_id":"298910979","publisher_name":"Rovio Entertainment Oyj","categories":[6014,7012,7001],"subtitle":"Best popular fun action game!","icon_url":"https://is2-ssl.mzstatic.com/image/thumb/Purple125/v4/f7/0f/fb/f70ffbc5-26a7-481d-1580-ef084efca299/AppIcon-1x_U007emarketing-0-7-0-85-220.png/1024x1024bb.png","offer":{"action_text":"GET","price":0,"price_formatted":"$0.00"},"on_card":true},{"app_id":1344700142,"name":"UNO!™","publisher_id":"1344700141","publisher_name":"Mattel163 Limited","categories":[6014,7005,7009,6016],"subtitle":"The World’s #1 Card Game","icon_url":"https://is1-ssl.mzstatic.com/image/thumb/Purple115/v4/1a/47/17/1a4717e8-7b1f-af09-bf70-e8f07540d167/AppIcon-0-0-1x_U007emarketing-0-0-0-7-0-0-sRGB-0-0-0-GLES2_U002c0-512MB-85-220-0-0.png/1024x1024bb.png","offer":{"action_text":"GET","price":0,"price_formatted":"$0.00"},"on_card":true},{"app_id":1361289299,"name":"Disney Wonderful Worlds","publisher_id":"293912963","publisher_name":"Ludia","categories":[6014,7015,7012],"subtitle":"Match & Build a Disney Park!","icon_url":"https://is1-ssl.mzstatic.com/image/thumb/Purple125/v4/c6/64/d1/c664d1e1-84e7-c133-7e8f-be6e448c07c1/AppIcon-0-0-1x_U007emarketing-0-0-0-7-0-0-sRGB-0-0-0-GLES2_U002c0-512MB-85-220-0-0.png/1024x1024bb.png","offer":{"action_text":"GET","price":0,"price_formatted":"$0.00"},"on_card":true},{"app_id":1581549121,"name":"Hundred Days","publisher_id":"1580509304","publisher_name":"Pixmain","categories":[6014,7015,7017],"subtitle":"A Winemaking Simulator Game","icon_url":"https://is2-ssl.mzstatic.com/image/thumb/Purple115/v4/5e/d8/24/5ed8248a-2a44-9f6e-3b6f-e77674c5b41a/AppIcon-0-0-1x_U007emarketing-0-0-0-7-0-0-sRGB-0-0-0-GLES2_U002c0-512MB-85-220-0-0.png/1024x1024bb.png","offer":{"action_text":"Buy","price":849,"price_formatted":"$8.49"},"on_card":true},{"app_id":1549696616,"name":"Soccer Manager 2022","publisher_id":"777728659","publisher_name":"Soccer Manager Ltd","categories":[6014,6004,7015,7016],"subtitle":"FIFPro™ Licensed Football Game","icon_url":"https://is5-ssl.mzstatic.com/image/thumb/Purple115/v4/11/e6/b0/11e6b02a-9ffa-5796-41f5-fff3eae26d64/AppIcon-1x_U007emarketing-0-7-0-85-220.png/1024x1024bb.png","offer":{"action_text":"GET","price":0,"price_formatted":"$0.00"},"on_card":true},{"app_id":1510325826,"name":"Switchcraft: Magical Match 3","publisher_id":"461402737","publisher_name":"wooga","categories":[6014,7012],"subtitle":"Choose how the mystery unfolds","icon_url":"https://is1-ssl.mzstatic.com/image/thumb/Purple115/v4/ec/50/75/ec507568-e705-7d5a-d7d4-e8ea9688b7c2/AppIcon-1x_U007emarketing-0-7-0-85-220.png/1024x1024bb.png","offer":{"action_text":"GET","price":0,"price_formatted":"$0.00"},"on_card":true},{"app_id":1517783697,"name":"Genshin Impact","publisher_id":"1286705195","publisher_name":"miHoYo Limited","categories":[6014,7014,7002],"subtitle":"Explore a World of Adventure","icon_url":"https://is2-ssl.mzstatic.com/image/thumb/Purple115/v4/4e/3d/e3/4e3de3ed-67db-358c-6e5a-0d8a1da047c0/AppIcon-1x_U007emarketing-0-7-0-0-85-220.png/1024x1024bb.png","offer":{"action_text":"GET","price":0,"price_formatted":"$0.00"},"on_card":true},{"app_id":1158967485,"name":"Hero Wars - Epic Fantasy","publisher_id":"660706304","publisher_name":"Nexters Global LTD","categories":[6014,6016,7002,7014],"subtitle":"Become a Legend!","icon_url":"https://is5-ssl.mzstatic.com/image/thumb/Purple115/v4/85/5c/b7/855cb778-af74-7143-93f9-f9506db322e1/AppIcon-0-0-1x_U007emarketing-0-0-0-7-0-0-sRGB-0-0-0-GLES2_U002c0-512MB-85-220-0-0.png/1024x1024bb.png","offer":{"action_text":"GET","price":0,"price_formatted":"$0.00"},"on_card":true},{"app_id":1187265767,"name":"Monument Valley 2","publisher_id":"297468910","publisher_name":"ustwo games","categories":[6014,7002,7012,6016],"subtitle":"A story of beauty and illusion","icon_url":"https://is4-ssl.mzstatic.com/image/thumb/Purple125/v4/f1/c1/81/f1c181e8-decf-1339-f9de-e9dfefb20994/AppIcon-0-0-1x_U007emarketing-0-0-0-7-0-0-sRGB-0-0-0-GLES2_U002c0-512MB-85-220-0-0.png/1024x1024bb.png","offer":{"action_text":"Buy","price":279,"price_formatted":"$2.79"},"on_card":true},{"app_id":1484442152,"name":"Merge Mansion","publisher_id":"974585521","publisher_name":"Metacore Games Oy","categories":[6014,7012],"subtitle":"Mansion full of mysteries!","icon_url":"https://is4-ssl.mzstatic.com/image/thumb/Purple115/v4/49/d3/57/49d357d4-f934-a641-7fcf-d4fa3fd49346/AppIcon-0-0-1x_U007emarketing-0-0-0-7-0-0-sRGB-0-0-0-GLES2_U002c0-512MB-85-220-0-0.png/1024x1024bb.png","offer":{"action_text":"GET","price":0,"price_formatted":"$0.00"},"on_card":true},{"app_id":1387853032,"name":"Hellrider 3","publisher_id":"973428904","publisher_name":"Andrey Chernyshov","categories":[6014,7013,6016,7001],"subtitle":"Ride, fight, save the world!","icon_url":"https://is4-ssl.mzstatic.com/image/thumb/Purple125/v4/8e/39/68/8e3968c0-cdf3-aa5d-5a09-e025cd230aec/AppIcon-0-0-1x_U007emarketing-0-0-0-7-0-0-sRGB-0-0-0-GLES2_U002c0-512MB-85-220-0-0.png/1024x1024bb.png","offer":{"action_text":"GET","price":0,"price_formatted":"$0.00"},"on_card":false}],"substyle":"list"},{"position":3,"id":"1509313372","url":"https://apps.apple.com/ca/story/id1509313372","title":"Rediscover Pokémon GO","label":"CATCH UP WITH A CLASSIC","short_description":"","style":"content","artwork":{"url":"https://is1-ssl.mzstatic.com/image/thumb/Features115/v4/1c/fc/18/1cfc18a1-f406-de8c-265d-09a7d2f5e11a/source/3524x2160bb.png","text_colors":["090c22","211015","1d2126","34251c"],"bg_color":"929037","alpha":false},"video_preview_url":null,"apps":[{"app_id":1094591345,"name":"Pokémon GO","publisher_id":"1037205060","publisher_name":"Niantic, Inc.","categories":[6014,7017,7014,6013],"subtitle":"Discover Pokémon worldwide","icon_url":"https://is5-ssl.mzstatic.com/image/thumb/Purple125/v4/4b/f7/0a/4bf70a14-4f92-da33-418a-906cfadb1f27/AppIcon-0-0-1x_U007emarketing-0-0-0-7-0-0-sRGB-0-0-0-GLES2_U002c0-512MB-85-220-0-0.png/1024x1024bb.png","offer":{"action_text":"GET","price":0,"price_formatted":"$0.00"},"on_card":true}],"substyle":"editorial"},{"position":4,"id":"1503357602","url":"https://apps.apple.com/ca/story/id1503357602","title":"Play Online With Friends","label":"GET COMPETITIVE","short_description":null,"style":"content","artwork":null,"video_preview_url":null,"apps":[{"app_id":1351168404,"name":"Among Us!","publisher_id":"957995279","publisher_name":"InnerSloth LLC","categories":[6014,7001,7015],"subtitle":null,"icon_url":"https://is5-ssl.mzstatic.com/image/thumb/Purple115/v4/7e/b6/3d/7eb63dbd-58d0-698e-9cfb-db98e7211537/AppIcon-1x_U007emarketing-0-7-0-85-220.png/1024x1024bb.png","offer":{"action_text":"GET","price":0,"price_formatted":"$0.00"},"on_card":true},{"app_id":1293634699,"name":"Mario Kart Tour","publisher_id":"1062496488","publisher_name":"Nintendo Co., Ltd.","categories":[6014,7001,7013],"subtitle":"Race around the world!","icon_url":"https://is3-ssl.mzstatic.com/image/thumb/Purple115/v4/41/78/bb/4178bb95-8695-c182-814b-9f271cfc2411/AppIcon-0-0-1x_U007emarketing-0-0-0-7-0-0-sRGB-0-0-0-GLES2_U002c0-512MB-85-220-0-0.png/1024x1024bb.png","offer":{"action_text":"GET","price":0,"price_formatted":"$0.00"},"on_card":true},{"app_id":1330123889,"name":"PUBG MOBILE: RESISTANCE","publisher_id":"504515421","publisher_name":"Tencent Mobile International Limited","categories":[6014,7001,7017],"subtitle":"Reunion: Classics Encore","icon_url":"https://is1-ssl.mzstatic.com/image/thumb/Purple125/v4/09/ca/90/09ca90a5-a162-539d-2505-3f4aade12192/AppIcon-1x_U007emarketing-0-0-GLES2_U002c0-512MB-sRGB-0-0-0-85-220-0-0-0-8.png/1024x1024bb.png","offer":{"action_text":"GET","price":0,"price_formatted":"$0.00"},"on_card":true},{"app_id":543186831,"name":"8 Ball Pool™","publisher_id":"337457683","publisher_name":"Miniclip.com","categories":[6014,6016,7016,7015],"subtitle":"Classic Pool Multiplayer Game","icon_url":"https://is5-ssl.mzstatic.com/image/thumb/Purple125/v4/bd/d0/5d/bdd05d99-5a1f-a61d-0967-9e3d2d409e79/AppIcon-0-0-1x_U007emarketing-0-0-0-7-0-0-sRGB-0-0-0-GLES2_U002c0-512MB-85-220-0-0.png/1024x1024bb.png","offer":{"action_text":"GET","price":0,"price_formatted":"$0.00"},"on_card":true},{"app_id":1053012308,"name":"Clash Royale","publisher_id":"488106216","publisher_name":"Supercell","categories":[6014,7017,6016,7001],"subtitle":"Epic Real-Time PvP Battles","icon_url":"https://is2-ssl.mzstatic.com/image/thumb/Purple115/v4/b3/ab/36/b3ab36da-6110-fca6-dc23-a260c3a9f0a7/AppIcon-1x_U007emarketing-6-0-85-220.png/1024x1024bb.png","offer":{"action_text":"GET","price":0,"price_formatted":"$0.00"},"on_card":true},{"app_id":479516143,"name":"Minecraft","publisher_id":"479516146","publisher_name":"Mojang","categories":[6014,7015,7002],"subtitle":"Create, explore and survive!","icon_url":"https://is4-ssl.mzstatic.com/image/thumb/Purple115/v4/1c/24/fb/1c24fb6b-6016-3265-8fb6-b9347d52d437/AppIcon-0-0-1x_U007emarketing-0-0-0-9-0-0-sRGB-0-0-0-GLES2_U002c0-512MB-85-220-0-0.png/1024x1024bb.png","offer":{"action_text":"Buy","price":999,"price_formatted":"$9.99"},"on_card":true},{"app_id":805603214,"name":"Asphalt 9: Legends","publisher_id":"282764297","publisher_name":"Gameloft","categories":[6014,7016,7013,6016],"subtitle":"Sport Car Racing Game","icon_url":"https://is4-ssl.mzstatic.com/image/thumb/Purple125/v4/dc/c8/44/dcc84402-48ee-5a6a-c5ec-f3e165312735/AppIcon-1x_U007emarketing-0-8-0-85-220.png/1024x1024bb.png","offer":{"action_text":"GET","price":0,"price_formatted":"$0.00"},"on_card":true},{"app_id":1336026283,"name":"BATTLESHIP","publisher_id":"988365603","publisher_name":"Marmalade Game Studio","categories":[6014,7004,7017],"subtitle":"The Classic Naval Combat Game","icon_url":"https://is2-ssl.mzstatic.com/image/thumb/Purple123/v4/15/7d/9f/157d9f7b-68f6-06ab-77a5-110f63167487/AppIcon-0-1x_U007emarketing-0-85-220-0-7.png/1024x1024bb.png","offer":{"action_text":"Buy","price":549,"price_formatted":"$5.49"},"on_card":true},{"app_id":553834731,"name":"Candy Crush Saga","publisher_id":"526656015","publisher_name":"King","categories":[6014,6016,7012,7003],"subtitle":"Play top match 3 puzzle games","icon_url":"https://is5-ssl.mzstatic.com/image/thumb/Purple125/v4/1d/9a/24/1d9a24f2-9a39-03dc-abf4-9028bf9dabba/AppIcon-1x_U007emarketing-0-7-0-85-220.png/1024x1024bb.png","offer":{"action_text":"GET","price":0,"price_formatted":"$0.00"},"on_card":true},{"app_id":1105855019,"name":"Gardenscapes","publisher_id":"1162116447","publisher_name":"Playrix","categories":[6014,6016,7012,7015],"subtitle":"Your gateway to acres of fun","icon_url":"https://is2-ssl.mzstatic.com/image/thumb/Purple125/v4/98/46/66/98466623-40d7-404c-b115-4fc2526ba4e5/AppIcon-1x_U007emarketing-0-10-0-85-220.png/1024x1024bb.png","offer":{"action_text":"GET","price":0,"price_formatted":"$0.00"},"on_card":true},{"app_id":1413826211,"name":"Golf Blitz","publisher_id":"370828169","publisher_name":"Noodlecake","categories":[6014,7001,7016,6016],"subtitle":"Multiplayer golf battles!","icon_url":"https://is1-ssl.mzstatic.com/image/thumb/Purple115/v4/01/45/a7/0145a73e-bbd3-d605-4f43-5e51cb9d0fd7/AppIcon-0-0-1x_U007emarketing-0-0-0-7-0-0-sRGB-0-0-0-GLES2_U002c0-512MB-85-220-0-0.png/1024x1024bb.png","offer":{"action_text":"GET","price":0,"price_formatted":"$0.00"},"on_card":true},{"app_id":1229016807,"name":"Brawl Stars","publisher_id":"488106216","publisher_name":"Supercell","categories":[6014,7003,6016,7001],"subtitle":"Epic 3v3 and Battle Royale","icon_url":"https://is5-ssl.mzstatic.com/image/thumb/Purple115/v4/6b/22/62/6b226256-f939-5bbd-273d-674fc67ee691/AppIcon-1x_U007emarketing-0-6-0-85-220.png/1024x1024bb.png","offer":{"action_text":"GET","price":0,"price_formatted":"$0.00"},"on_card":true}],"substyle":"grid"},{"position":5,"id":"1554641308","url":"https://apps.apple.com/ca/story/id1554641308","title":"Water tracker Waterllama","label":"APP\nOF THE\nDAY","short_description":"A quirky companion for building healthy hydration habits.","style":"branded","artwork":{"url":"https://is5-ssl.mzstatic.com/image/thumb/Features124/v4/1e/b5/66/1eb566d5-96bd-4113-3378-6f219c40005e/source/3524x2160bb.png","text_colors":["0c0908","0d0908","0c2225","0c2225"],"bg_color":"17b2d4","alpha":false},"video_preview_url":null,"apps":[{"app_id":1454778585,"name":"Water drink reminder Waterlama","publisher_id":"1174362651","publisher_name":"Vitalii Mogylevets","categories":[6013,6023],"subtitle":"My water tracker — minder app","icon_url":"https://is3-ssl.mzstatic.com/image/thumb/Purple115/v4/8b/10/b7/8b10b702-724b-4441-a558-537d5426ae63/AppIcon-0-0-1x_U007emarketing-0-0-0-7-0-0-sRGB-0-0-0-GLES2_U002c0-512MB-85-220-0-0.png/1024x1024bb.png","offer":{"action_text":"GET","price":0,"price_formatted":"$0.00"},"on_card":true}],"substyle":"app_of_day"},{"position":6,"id":"1573514222","url":"https://apps.apple.com/ca/story/id1573514222","title":"Bloons Pop!","label":"GAME\nOF THE\nDAY","short_description":"Quit monkeying around and blast these balloons!","style":"branded","artwork":{"url":"https://is3-ssl.mzstatic.com/image/thumb/Features115/v4/91/a8/46/91a84653-6324-1c68-841a-91dc288e3c46/source/3524x2160bb.png","text_colors":["1e1a0e","2d180b","21392e","2d372b"],"bg_color":"34dde8","alpha":false},"video_preview_url":null,"apps":[{"app_id":1525285422,"name":"Bloons Pop!","publisher_id":"386241773","publisher_name":"Ninja Kiwi","categories":[6014,6016,7012,7003],"subtitle":"Pop Bloons to fix Monkey Town!","icon_url":"https://is3-ssl.mzstatic.com/image/thumb/Purple125/v4/eb/0b/a5/eb0ba554-f89e-fc01-43bb-7b839a05bf82/AppIcon-1x_U007emarketing-0-7-0-85-220.png/1024x1024bb.png","offer":{"action_text":"GET","price":0,"price_formatted":"$0.00"},"on_card":true}],"substyle":"game_of_day"}]}